{"league": "nba", "code": "200701230LAC", "season": "2006-2007", "away": {"players": {"Ruben Patterson": {"STL%": 0.0, "": "us", "FT": 2.0, "weight": "224", "3P": 0.0, "TOV": 1.0, "STL/TOV": 0.0, "TSA": 17.2, "2PA": 15.0, "college": "University of Cincinnati", "FG": 7.0, "3PA": 0.0, "DRB": 4.0, "ORB%": 7.0, "BLK%": 1.9, "AST/TOV": 4.0, "position": "SF", "AST": 4.0, "FT%": 0.4, "3PAr": 0.0, "PF": 2.0, "PTS": 16.0, "FGA": 15.0, "DRBr": 0.6666666666666666, "ORBr": 0.3333333333333333, "2P": 7.0, "STL": 0.0, "TRB": 6.0, "TOV%": 5.5, "AST%": 20.4, "FTAr": 0.3333333333333333, "FTA": 5.0, "FIC": 10.875, "eFG%": 0.4666666666666667, "BLK": 1.0, "birth_date": "1975-07-31", "FG%": 0.4666666666666667, "2PAr": 1.0, "FTr": 0.333, "+/-": -15.0, "name": "Ruben Patterson", "USG%": 25.3, "DRB%": 14.7, "TS%": 0.46511627906976744, "experience": 8, "height": 1.9812240916849548, "2P%": 0.4666666666666667, "MP": 32.71666666666667, "DRtg": 121.0, "ORtg": 101.0, "TRB%": 10.7, "FT/FGA": 0.13333333333333333, "ORB": 2.0, "3P%": null, "HOB": 0.28205128205128205}, "Julius Hodge": {"STL%": 10.0, "": "us", "FT": 1.0, "weight": "210", "3P": 0.0, "TOV": 1.0, "STL/TOV": 1.0, "TSA": 1.88, "2PA": 1.0, "college": "North Carolina State University", "FG": 1.0, "3PA": 0.0, "DRB": 1.0, "ORB%": 0.0, "BLK%": 0.0, "AST/TOV": 1.0, "position": "SG", "AST": 1.0, "FT%": 0.5, "3PAr": 0.0, "PF": 2.0, "PTS": 3.0, "FGA": 1.0, "DRBr": 1.0, "ORBr": 0.0, "2P": 1.0, "STL": 1.0, "TRB": 1.0, "TOV%": 34.7, "AST%": 32.5, "FTAr": 2.0, "FTA": 2.0, "FIC": 2.25, "eFG%": 1.0, "BLK": 0.0, "birth_date": "1983-11-18", "FG%": 1.0, "2PAr": 1.0, "FTr": 2.0, "+/-": 5.0, "name": "Julius Hodge", "USG%": 26.2, "DRB%": 23.9, "TS%": 0.797872340425532, "experience": 1, "height": 2.042184832967569, "2P%": 1.0, "MP": 5.016666666666667, "DRtg": 100.0, "ORtg": 106.0, "TRB%": 11.7, "FT/FGA": 1.0, "ORB": 0.0, "3P%": null, "HOB": 0.05128205128205128}, "Lynn Greer": {"STL%": 0.0, "": "us", "FT": 0.0, "weight": "175", "3P": 0.0, "TOV": 0.0, "STL/TOV": null, "TSA": 3.0, "2PA": 3.0, "college": "Temple University", "FG": 1.0, "3PA": 0.0, "DRB": 0.0, "ORB%": 0.0, "BLK%": 0.0, "AST/TOV": null, "position": "SG", "AST": 3.0, "FT%": null, "3PAr": 0.0, "PF": 0.0, "PTS": 2.0, "FGA": 3.0, "DRBr": null, "ORBr": null, "2P": 1.0, "STL": 0.0, "TRB": 0.0, "TOV%": 0.0, "AST%": 51.0, "FTAr": 0.0, "FTA": 0.0, "FIC": 2.75, "eFG%": 0.3333333333333333, "BLK": 0.0, "birth_date": "1979-10-23", "FG%": 0.3333333333333333, "2PAr": 1.0, "FTr": 0.0, "+/-": 3.0, "name": "Lynn Greer", "USG%": 16.1, "DRB%": 0.0, "TS%": 0.3333333333333333, "experience": 0, "height": 1.889782979761034, "2P%": 0.3333333333333333, "MP": 8.466666666666667, "DRtg": 126.0, "ORtg": 104.0, "TRB%": 0.0, "FT/FGA": 0.0, "ORB": 0.0, "3P%": null, "HOB": 0.10256410256410256}, "Andrew Bogut": {"STL%": 2.6, "": "au", "FT": 0.0, "weight": "260", "3P": 0.0, "TOV": 0.0, "STL/TOV": null, "TSA": 7.0, "2PA": 7.0, "college": "University of Utah", "FG": 3.0, "3PA": 0.0, "DRB": 1.0, "ORB%": 5.9, "BLK%": 0.0, "AST/TOV": null, "position": "C", "AST": 3.0, "FT%": null, "3PAr": 0.0, "PF": 6.0, "PTS": 6.0, "FGA": 7.0, "DRBr": 0.5, "ORBr": 0.5, "2P": 3.0, "STL": 1.0, "TRB": 2.0, "TOV%": 0.0, "AST%": 23.7, "FTAr": 0.0, "FTA": 0.0, "FIC": 3.5, "eFG%": 0.42857142857142855, "BLK": 0.0, "birth_date": "1984-11-28", "FG%": 0.42857142857142855, "2PAr": 1.0, "FTr": 0.0, "+/-": -12.0, "name": "Andrew Bogut", "USG%": 16.6, "DRB%": 6.2, "TS%": 0.42857142857142855, "experience": 1, "height": 2.13362594489149, "2P%": 0.42857142857142855, "MP": 19.25, "DRtg": 119.0, "ORtg": 108.0, "TRB%": 6.1, "FT/FGA": 0.0, "ORB": 1.0, "3P%": null, "HOB": 0.15384615384615385}, "Damir Markota": {"STL%": 0.0, "": "ba", "FT": 0.0, "weight": "225", "3P": 2.0, "TOV": 0.0, "STL/TOV": null, "TSA": 4.0, "2PA": 2.0, "college": "", "FG": 3.0, "3PA": 2.0, "DRB": 1.0, "ORB%": 0.0, "BLK%": 0.0, "AST/TOV": null, "position": "PF", "AST": 0.0, "FT%": null, "3PAr": 0.5, "PF": 2.0, "PTS": 8.0, "FGA": 4.0, "DRBr": 1.0, "ORBr": 0.0, "2P": 1.0, "STL": 0.0, "TRB": 1.0, "TOV%": 0.0, "AST%": 0.0, "FTAr": 0.0, "FTA": 0.0, "FIC": 4.75, "eFG%": 1.0, "BLK": 0.0, "birth_date": "1985-12-26", "FG%": 0.75, "2PAr": 0.5, "FTr": 0.0, "+/-": 4.0, "name": "Damir Markota", "USG%": 24.0, "DRB%": 15.8, "TS%": 1.0, "experience": 0, "height": 1.8593026091197267, "2P%": 0.5, "MP": 7.6, "DRtg": 122.0, "ORtg": 174.0, "TRB%": 7.7, "FT/FGA": 0.0, "ORB": 0.0, "3P%": 1.0, "HOB": 0.07692307692307693}, "Earl Boykins": {"STL%": 0.0, "": "us", "FT": 1.0, "weight": "135", "3P": 1.0, "TOV": 3.0, "STL/TOV": 0.0, "TSA": 15.44, "2PA": 11.0, "college": "Eastern Michigan University", "FG": 6.0, "3PA": 4.0, "DRB": 4.0, "ORB%": 0.0, "BLK%": 0.0, "AST/TOV": 1.6666666666666667, "position": "PG", "AST": 5.0, "FT%": 1.0, "3PAr": 0.26666666666666666, "PF": 2.0, "PTS": 14.0, "FGA": 15.0, "DRBr": 1.0, "ORBr": 0.0, "2P": 5.0, "STL": 0.0, "TRB": 4.0, "TOV%": 16.3, "AST%": 19.1, "FTAr": 0.06666666666666667, "FTA": 1.0, "FIC": 6.375, "eFG%": 0.43333333333333335, "BLK": 0.0, "birth_date": "1976-06-02", "FG%": 0.4, "2PAr": 0.7333333333333333, "FTr": 0.067, "+/-": -22.0, "name": "Earl Boykins", "USG%": 21.3, "DRB%": 12.1, "TS%": 0.4533678756476684, "experience": 8, "height": 1.6764203852718849, "2P%": 0.45454545454545453, "MP": 39.53333333333333, "DRtg": 123.0, "ORtg": 86.0, "TRB%": 5.9, "FT/FGA": 0.06666666666666667, "ORB": 0.0, "3P%": 0.25, "HOB": 0.28205128205128205}, "Dan Gadzuric": {"STL%": 3.5, "": "nl", "FT": 2.0, "weight": "240", "3P": 0.0, "TOV": 1.0, "STL/TOV": 1.0, "TSA": 2.88, "2PA": 2.0, "college": "University of California, Los Angeles", "FG": 2.0, "3PA": 0.0, "DRB": 2.0, "ORB%": 0.0, "BLK%": 0.0, "AST/TOV": 0.0, "position": "C", "AST": 0.0, "FT%": 1.0, "3PAr": 0.0, "PF": 2.0, "PTS": 6.0, "FGA": 2.0, "DRBr": 1.0, "ORBr": 0.0, "2P": 2.0, "STL": 1.0, "TRB": 2.0, "TOV%": 25.8, "AST%": 0.0, "FTAr": 1.0, "FTA": 2.0, "FIC": 4.25, "eFG%": 1.0, "BLK": 0.0, "birth_date": "1978-02-02", "FG%": 1.0, "2PAr": 1.0, "FTr": 1.0, "+/-": -2.0, "name": "Dan Gadzuric", "USG%": 12.3, "DRB%": 16.7, "TS%": 1.0416666666666667, "experience": 4, "height": 1.8623506461838577, "2P%": 1.0, "MP": 14.35, "DRtg": 115.0, "ORtg": 146.0, "TRB%": 8.2, "FT/FGA": 1.0, "ORB": 0.0, "3P%": null, "HOB": 0.05128205128205128}, "Ersan Ilyasova": {"STL%": 2.2, "": "tr", "FT": 3.0, "weight": "235", "3P": 2.0, "TOV": 1.0, "STL/TOV": 1.0, "TSA": 11.76, "2PA": 5.0, "college": "", "FG": 3.0, "3PA": 5.0, "DRB": 1.0, "ORB%": 14.8, "BLK%": 0.0, "AST/TOV": 1.0, "position": "PF", "AST": 1.0, "FT%": 0.75, "3PAr": 0.5, "PF": 3.0, "PTS": 11.0, "FGA": 10.0, "DRBr": 0.25, "ORBr": 0.75, "2P": 1.0, "STL": 1.0, "TRB": 4.0, "TOV%": 7.8, "AST%": 6.3, "FTAr": 0.4, "FTA": 4.0, "FIC": 5.25, "eFG%": 0.4, "BLK": 0.0, "birth_date": "1987-05-15", "FG%": 0.3, "2PAr": 0.5, "FTr": 0.4, "+/-": -13.0, "name": "Ersan Ilyasova", "USG%": 25.1, "DRB%": 5.2, "TS%": 0.467687074829932, "experience": 0, "height": 1.8593026091197267, "2P%": 0.2, "MP": 23.116666666666667, "DRtg": 120.0, "ORtg": 102.0, "TRB%": 10.1, "FT/FGA": 0.3, "ORB": 3.0, "3P%": 0.4, "HOB": 0.10256410256410256}, "David Noel": {"STL%": 0.0, "": "us", "FT": 0.0, "weight": "230", "3P": 0.0, "TOV": 1.0, "STL/TOV": 0.0, "TSA": 4.0, "2PA": 3.0, "college": "University of North Carolina", "FG": 1.0, "3PA": 1.0, "DRB": 1.0, "ORB%": 5.3, "BLK%": 0.0, "AST/TOV": 2.0, "position": "PF", "AST": 2.0, "FT%": null, "3PAr": 0.25, "PF": 4.0, "PTS": 2.0, "FGA": 4.0, "DRBr": 0.5, "ORBr": 0.5, "2P": 1.0, "STL": 0.0, "TRB": 2.0, "TOV%": 20.0, "AST%": 12.1, "FTAr": 0.0, "FTA": 0.0, "FIC": -0.25, "eFG%": 0.25, "BLK": 0.0, "birth_date": "1984-02-27", "FG%": 0.25, "2PAr": 0.75, "FTr": 0.0, "+/-": -12.0, "name": "David Noel", "USG%": 10.6, "DRB%": 5.6, "TS%": 0.25, "experience": 0, "height": 2.0117044623262617, "2P%": 0.3333333333333333, "MP": 21.516666666666666, "DRtg": 125.0, "ORtg": 68.0, "TRB%": 5.4, "FT/FGA": 0.0, "ORB": 1.0, "3P%": 0.0, "HOB": 0.07692307692307693}, "Brian Skinner": {"STL%": 0.0, "": "us", "FT": 0.0, "weight": "255", "3P": 0.0, "TOV": 2.0, "STL/TOV": 0.0, "TSA": 6.88, "2PA": 6.0, "college": "Baylor University", "FG": 2.0, "3PA": 0.0, "DRB": 7.0, "ORB%": 3.6, "BLK%": 1.9, "AST/TOV": 0.0, "position": "PF", "AST": 0.0, "FT%": 0.0, "3PAr": 0.0, "PF": 2.0, "PTS": 4.0, "FGA": 6.0, "DRBr": 0.875, "ORBr": 0.125, "2P": 2.0, "STL": 0.0, "TRB": 8.0, "TOV%": 22.5, "AST%": 0.0, "FTAr": 0.3333333333333333, "FTA": 2.0, "FIC": 3.0, "eFG%": 0.3333333333333333, "BLK": 1.0, "birth_date": "1976-05-19", "FG%": 0.3333333333333333, "2PAr": 1.0, "FTr": 0.333, "+/-": -13.0, "name": "Brian Skinner", "USG%": 12.7, "DRB%": 26.4, "TS%": 0.29069767441860467, "experience": 8, "height": 2.103145574250183, "2P%": 0.3333333333333333, "MP": 31.866666666666667, "DRtg": 118.0, "ORtg": 51.0, "TRB%": 14.7, "FT/FGA": 0.0, "ORB": 1.0, "3P%": null, "HOB": 0.05128205128205128}, "Charlie Bell": {"STL%": 1.4, "": "us", "FT": 3.0, "weight": "200", "3P": 1.0, "TOV": 0.0, "STL/TOV": null, "TSA": 21.32, "2PA": 16.0, "college": "Michigan State University", "FG": 10.0, "3PA": 4.0, "DRB": 6.0, "ORB%": 0.0, "BLK%": 0.0, "AST/TOV": null, "position": "SG", "AST": 3.0, "FT%": 1.0, "3PAr": 0.2, "PF": 1.0, "PTS": 24.0, "FGA": 20.0, "DRBr": 1.0, "ORBr": 0.0, "2P": 9.0, "STL": 1.0, "TRB": 6.0, "TOV%": 0.0, "AST%": 15.2, "FTAr": 0.15, "FTA": 3.0, "FIC": 15.875, "eFG%": 0.525, "BLK": 0.0, "birth_date": "1979-03-12", "FG%": 0.5, "2PAr": 0.8, "FTr": 0.15, "+/-": -18.0, "name": "Charlie Bell", "USG%": 26.6, "DRB%": 19.7, "TS%": 0.5628517823639775, "experience": 2, "height": 1.9202633504023408, "2P%": 0.5625, "MP": 36.583333333333336, "DRtg": 119.0, "ORtg": 118.0, "TRB%": 9.6, "FT/FGA": 0.15, "ORB": 0.0, "3P%": 0.25, "HOB": 0.3333333333333333}}, "scores": {"1": "24", "3": "16", "2": "34", "4": "22", "T": "96"}, "name": "Milwaukee Bucks", "totals": {"STL%": 5.2, "FT": 12.0, "2PA": 71.0, "FG": 39.0, "DRB": 28.0, "ORB%": 19.0, "AST": 22.0, "3PAr": 0.1839080459770115, "PF": 26.0, "FGA": 87.0, "DRBr": 0.7777777777777778, "2P": 33.0, "ORBr": 0.2222222222222222, "TOV%": 9.5, "AST%": 56.4, "FTAr": 0.21839080459770116, "FIC": 58.625, "eFG%": 0.4827586206896552, "FG%": 0.4482758620689655, "2PAr": 0.8160919540229885, "+/-": -19.0, "USG%": 100.0, "DRtg": 120.4, "2P%": 0.4647887323943662, "DRB%": 70.0, "ORtg": 100.5, "TRB%": 43.9, "ORB": 8.0, "3P": 6.0, "TOV": 10.0, "STL/TOV": 0.5, "TSA": 95.36, "AST/TOV": 2.2, "3PA": 16.0, "BLK%": 2.6, "FT%": 0.631578947368421, "PTS": 96.0, "HOB": 1.564102564102564, "STL": 5.0, "TRB": 36.0, "FTA": 19.0, "BLK": 2.0, "FTr": 0.218, "TS%": 0.5033557046979866, "FT/FGA": 0.13793103448275862, "3P%": 0.375}}, "time": "19:30:00", "country": "United States", "date": "2007-01-23", "home": {"players": {"Paul Davis": {"STL%": 6.7, "": "us", "FT": 0.0, "weight": "270", "3P": 0.0, "TOV": 0.0, "STL/TOV": null, "TSA": 3.0, "2PA": 3.0, "college": "Michigan State University", "FG": 1.0, "3PA": 0.0, "DRB": 2.0, "ORB%": 31.9, "BLK%": 0.0, "AST/TOV": null, "position": "C", "AST": 0.0, "FT%": null, "3PAr": 0.0, "PF": 1.0, "PTS": 2.0, "FGA": 3.0, "DRBr": 0.5, "ORBr": 0.5, "2P": 1.0, "STL": 1.0, "TRB": 4.0, "TOV%": 0.0, "AST%": 0.0, "FTAr": 0.0, "FTA": 0.0, "FIC": 3.75, "eFG%": 0.3333333333333333, "BLK": 0.0, "birth_date": "1984-07-21", "FG%": 0.3333333333333333, "2PAr": 1.0, "FTr": 0.0, "+/-": -2.0, "name": "Paul Davis", "USG%": 17.3, "DRB%": 30.3, "TS%": 0.3333333333333333, "experience": 0, "height": 1.8623506461838577, "2P%": 0.3333333333333333, "MP": 7.533333333333333, "DRtg": 90.0, "ORtg": 107.0, "TRB%": 31.1, "FT/FGA": 0.0, "ORB": 2.0, "3P%": null, "HOB": 0.022222222222222223}, "Elton Brand": {"STL%": 4.5, "": "us", "FT": 5.0, "weight": "275", "3P": 0.0, "TOV": 1.0, "STL/TOV": 3.0, "TSA": 17.64, "2PA": 15.0, "college": "Duke University", "FG": 10.0, "3PA": 0.0, "DRB": 5.0, "ORB%": 7.2, "BLK%": 6.1, "AST/TOV": 5.0, "position": "PF", "AST": 5.0, "FT%": 0.8333333333333334, "3PAr": 0.0, "PF": 1.0, "PTS": 25.0, "FGA": 15.0, "DRBr": 0.7142857142857143, "ORBr": 0.2857142857142857, "2P": 10.0, "STL": 3.0, "TRB": 7.0, "TOV%": 5.4, "AST%": 23.4, "FTAr": 0.4, "FTA": 6.0, "FIC": 26.75, "eFG%": 0.6666666666666666, "BLK": 3.0, "birth_date": "1979-03-11", "FG%": 0.6666666666666666, "2PAr": 1.0, "FTr": 0.4, "+/-": 13.0, "name": "Elton Brand", "USG%": 24.2, "DRB%": 17.1, "TS%": 0.7086167800453514, "experience": 7, "height": 2.0726652036088757, "2P%": 0.6666666666666666, "MP": 33.46666666666667, "DRtg": 92.0, "ORtg": 145.0, "TRB%": 12.2, "FT/FGA": 0.3333333333333333, "ORB": 2.0, "3P%": null, "HOB": 0.3333333333333333}, "Tim Thomas": {"STL%": 0.0, "": "us", "FT": 2.0, "weight": "230", "3P": 1.0, "TOV": 1.0, "STL/TOV": 0.0, "TSA": 7.88, "2PA": 3.0, "college": "Villanova University", "FG": 3.0, "3PA": 4.0, "DRB": 3.0, "ORB%": 17.2, "BLK%": 0.0, "AST/TOV": 2.0, "position": "PF", "AST": 2.0, "FT%": 1.0, "3PAr": 0.5714285714285714, "PF": 1.0, "PTS": 9.0, "FGA": 7.0, "DRBr": 0.5, "ORBr": 0.5, "2P": 2.0, "STL": 0.0, "TRB": 6.0, "TOV%": 11.3, "AST%": 12.0, "FTAr": 0.2857142857142857, "FTA": 2.0, "FIC": 8.75, "eFG%": 0.5, "BLK": 0.0, "birth_date": "1977-02-26", "FG%": 0.42857142857142855, "2PAr": 0.42857142857142855, "FTr": 0.286, "+/-": 11.0, "name": "Tim Thomas", "USG%": 18.4, "DRB%": 16.3, "TS%": 0.5710659898477157, "experience": 9, "height": 1.8593026091197267, "2P%": 0.6666666666666666, "MP": 20.983333333333334, "DRtg": 108.0, "ORtg": 125.0, "TRB%": 16.7, "FT/FGA": 0.2857142857142857, "ORB": 3.0, "3P%": 0.25, "HOB": 0.1111111111111111}, "Chris Kaman": {"STL%": 0.0, "": "us", "FT": 1.0, "weight": "265", "3P": 0.0, "TOV": 0.0, "STL/TOV": null, "TSA": 9.88, "2PA": 9.0, "college": "Central Michigan University", "FG": 5.0, "3PA": 0.0, "DRB": 11.0, "ORB%": 0.0, "BLK%": 14.6, "AST/TOV": null, "position": "C", "AST": 2.0, "FT%": 0.5, "3PAr": 0.0, "PF": 4.0, "PTS": 11.0, "FGA": 9.0, "DRBr": 1.0, "ORBr": 0.0, "2P": 5.0, "STL": 0.0, "TRB": 11.0, "TOV%": 0.0, "AST%": 9.5, "FTAr": 0.2222222222222222, "FTA": 2.0, "FIC": 17.75, "eFG%": 0.5555555555555556, "BLK": 6.0, "birth_date": "1982-04-28", "FG%": 0.5555555555555556, "2PAr": 1.0, "FTr": 0.222, "+/-": 13.0, "name": "Chris Kaman", "USG%": 15.4, "DRB%": 45.2, "TS%": 0.5566801619433198, "experience": 3, "height": 2.13362594489149, "2P%": 0.5555555555555556, "MP": 27.783333333333335, "DRtg": 87.0, "ORtg": 121.0, "TRB%": 23.2, "FT/FGA": 0.1111111111111111, "ORB": 0.0, "3P%": null, "HOB": 0.15555555555555556}, "Shaun Livingston": {"STL%": 0.0, "": "us", "FT": 0.0, "weight": "192", "3P": 0.0, "TOV": 1.0, "STL/TOV": 0.0, "TSA": 6.0, "2PA": 6.0, "college": "", "FG": 4.0, "3PA": 0.0, "DRB": 1.0, "ORB%": 0.0, "BLK%": 0.0, "AST/TOV": 2.0, "position": "PG", "AST": 2.0, "FT%": null, "3PAr": 0.0, "PF": 1.0, "PTS": 8.0, "FGA": 6.0, "DRBr": 1.0, "ORBr": 0.0, "2P": 4.0, "STL": 0.0, "TRB": 1.0, "TOV%": 14.3, "AST%": 12.5, "FTAr": 0.0, "FTA": 0.0, "FIC": 4.75, "eFG%": 0.6666666666666666, "BLK": 0.0, "birth_date": "1985-09-11", "FG%": 0.6666666666666666, "2PAr": 1.0, "FTr": 0.0, "+/-": 11.0, "name": "Shaun Livingston", "USG%": 14.2, "DRB%": 5.3, "TS%": 0.6666666666666666, "experience": 2, "height": 2.042184832967569, "2P%": 0.6666666666666666, "MP": 21.4, "DRtg": 110.0, "ORtg": 116.0, "TRB%": 2.7, "FT/FGA": 0.0, "ORB": 0.0, "3P%": null, "HOB": 0.13333333333333333}, "Alvin Williams": {"STL%": 10.0, "": "us", "FT": 2.0, "weight": "185", "3P": 0.0, "TOV": 2.0, "STL/TOV": 0.5, "TSA": 2.76, "2PA": 1.0, "college": "Villanova University", "FG": 0.0, "3PA": 0.0, "DRB": 0.0, "ORB%": 23.9, "BLK%": 0.0, "AST/TOV": 0.0, "position": "PG", "AST": 0.0, "FT%": 0.5, "3PAr": 0.0, "PF": 0.0, "PTS": 2.0, "FGA": 1.0, "DRBr": 0.0, "ORBr": 1.0, "2P": 0.0, "STL": 1.0, "TRB": 1.0, "TOV%": 42.0, "AST%": 0.0, "FTAr": 4.0, "FTA": 4.0, "FIC": -0.25, "eFG%": 0.0, "BLK": 0.0, "birth_date": "1974-08-06", "FG%": 0.0, "2PAr": 1.0, "FTr": 4.0, "+/-": -5.0, "name": "Alvin Williams", "USG%": 41.2, "DRB%": 0.0, "TS%": 0.3623188405797102, "experience": 8, "height": 1.9812240916849548, "2P%": 0.0, "MP": 5.016666666666667, "DRtg": 90.0, "ORtg": 57.0, "TRB%": 11.7, "FT/FGA": 2.0, "ORB": 1.0, "3P%": null, "HOB": 0.0}, "James Singleton": {"STL%": 0.0, "": "us", "FT": 0.0, "weight": "216", "3P": 0.0, "TOV": 0.0, "STL/TOV": null, "TSA": 2.0, "2PA": 2.0, "college": "Murray State University", "FG": 0.0, "3PA": 0.0, "DRB": 1.0, "ORB%": 31.3, "BLK%": 35.3, "AST/TOV": null, "position": "PF", "AST": 0.0, "FT%": null, "3PAr": 0.0, "PF": 0.0, "PTS": 0.0, "FGA": 2.0, "DRBr": 0.5, "ORBr": 0.5, "2P": 0.0, "STL": 0.0, "TRB": 2.0, "TOV%": 0.0, "AST%": 0.0, "FTAr": 0.0, "FTA": 0.0, "FIC": 2.25, "eFG%": 0.0, "BLK": 2.0, "birth_date": "1981-07-20", "FG%": 0.0, "2PAr": 1.0, "FTr": 0.0, "+/-": 0.0, "name": "James Singleton", "USG%": 22.6, "DRB%": 29.8, "TS%": 0.0, "experience": 1, "height": 2.0726652036088757, "2P%": 0.0, "MP": 3.8333333333333335, "DRtg": 71.0, "ORtg": 44.0, "TRB%": 30.5, "FT/FGA": 0.0, "ORB": 1.0, "3P%": null, "HOB": 0.0}, "Sam Cassell": {"STL%": 0.0, "": "us", "FT": 4.0, "weight": "185", "3P": 0.0, "TOV": 1.0, "STL/TOV": 0.0, "TSA": 10.76, "2PA": 8.0, "college": "Florida State University", "FG": 2.0, "3PA": 1.0, "DRB": 1.0, "ORB%": 0.0, "BLK%": 0.0, "AST/TOV": 8.0, "position": "PG", "AST": 8.0, "FT%": 1.0, "3PAr": 0.1111111111111111, "PF": 1.0, "PTS": 8.0, "FGA": 9.0, "DRBr": 1.0, "ORBr": 0.0, "2P": 2.0, "STL": 0.0, "TRB": 1.0, "TOV%": 8.5, "AST%": 41.7, "FTAr": 0.4444444444444444, "FTA": 4.0, "FIC": 7.0, "eFG%": 0.2222222222222222, "BLK": 0.0, "birth_date": "1969-11-18", "FG%": 0.2222222222222222, "2PAr": 0.8888888888888888, "FTr": 0.444, "+/-": 15.0, "name": "Sam Cassell", "USG%": 22.6, "DRB%": 5.1, "TS%": 0.3717472118959108, "experience": 13, "height": 1.9202633504023408, "2P%": 0.25, "MP": 22.6, "DRtg": 110.0, "ORtg": 103.0, "TRB%": 2.6, "FT/FGA": 0.4444444444444444, "ORB": 0.0, "3P%": 0.0, "HOB": 0.2222222222222222}, "Corey Maggette": {"STL%": 0.0, "": "us", "FT": 7.0, "weight": "218", "3P": 0.0, "TOV": 1.0, "STL/TOV": 0.0, "TSA": 11.52, "2PA": 7.0, "college": "Duke University", "FG": 4.0, "3PA": 1.0, "DRB": 3.0, "ORB%": 4.4, "BLK%": 0.0, "AST/TOV": 4.0, "position": "SF", "AST": 4.0, "FT%": 0.875, "3PAr": 0.125, "PF": 4.0, "PTS": 15.0, "FGA": 8.0, "DRBr": 0.75, "ORBr": 0.25, "2P": 4.0, "STL": 0.0, "TRB": 4.0, "TOV%": 8.0, "AST%": 18.3, "FTAr": 1.0, "FTA": 8.0, "FIC": 10.25, "eFG%": 0.5, "BLK": 0.0, "birth_date": "1979-11-12", "FG%": 0.5, "2PAr": 0.875, "FTr": 1.0, "+/-": 10.0, "name": "Corey Maggette", "USG%": 19.7, "DRB%": 12.5, "TS%": 0.6510416666666667, "experience": 7, "height": 2.0117044623262617, "2P%": 0.5714285714285714, "MP": 27.533333333333335, "DRtg": 108.0, "ORtg": 138.0, "TRB%": 8.5, "FT/FGA": 0.875, "ORB": 1.0, "3P%": 0.0, "HOB": 0.17777777777777778}, "Quinton Ross": {"STL%": 2.0, "": "us", "FT": 1.0, "weight": "195", "3P": 0.0, "TOV": 1.0, "STL/TOV": 1.0, "TSA": 9.44, "2PA": 9.0, "college": "Southern Methodist University", "FG": 6.0, "3PA": 0.0, "DRB": 1.0, "ORB%": 9.5, "BLK%": 0.0, "AST/TOV": 4.0, "position": "SG", "AST": 4.0, "FT%": 1.0, "3PAr": 0.0, "PF": 2.0, "PTS": 13.0, "FGA": 9.0, "DRBr": 0.3333333333333333, "ORBr": 0.6666666666666666, "2P": 6.0, "STL": 1.0, "TRB": 3.0, "TOV%": 9.6, "AST%": 22.5, "FTAr": 0.1111111111111111, "FTA": 1.0, "FIC": 11.625, "eFG%": 0.6666666666666666, "BLK": 0.0, "birth_date": "1981-04-30", "FG%": 0.6666666666666666, "2PAr": 1.0, "FTr": 0.111, "+/-": 15.0, "name": "Quinton Ross", "USG%": 17.9, "DRB%": 4.5, "TS%": 0.6885593220338984, "experience": 2, "height": 2.0117044623262617, "2P%": 0.6666666666666666, "MP": 25.35, "DRtg": 106.0, "ORtg": 137.0, "TRB%": 6.9, "FT/FGA": 0.1111111111111111, "ORB": 2.0, "3P%": null, "HOB": 0.2222222222222222}, "Cuttino Mobley": {"STL%": 2.9, "": "us", "FT": 2.0, "weight": "190", "3P": 0.0, "TOV": 2.0, "STL/TOV": 1.0, "TSA": 16.76, "2PA": 13.0, "college": "University of Rhode Island", "FG": 10.0, "3PA": 2.0, "DRB": 6.0, "ORB%": 0.0, "BLK%": 0.0, "AST/TOV": 1.0, "position": "SG", "AST": 2.0, "FT%": 0.5, "3PAr": 0.13333333333333333, "PF": 1.0, "PTS": 22.0, "FGA": 15.0, "DRBr": 1.0, "ORBr": 0.0, "2P": 10.0, "STL": 2.0, "TRB": 6.0, "TOV%": 10.7, "AST%": 8.8, "FTAr": 0.26666666666666666, "FTA": 4.0, "FIC": 15.25, "eFG%": 0.6666666666666666, "BLK": 0.0, "birth_date": "1975-09-01", "FG%": 0.6666666666666666, "2PAr": 0.8666666666666667, "FTr": 0.267, "+/-": 13.0, "name": "Cuttino Mobley", "USG%": 23.2, "DRB%": 19.6, "TS%": 0.6563245823389021, "experience": 8, "height": 1.9507437210436478, "2P%": 0.7692307692307693, "MP": 35.016666666666666, "DRtg": 101.0, "ORtg": 116.0, "TRB%": 10.0, "FT/FGA": 0.13333333333333333, "ORB": 0.0, "3P%": 0.0, "HOB": 0.26666666666666666}, "Daniel Ewing": {"STL%": 0.0, "": "us", "FT": 0.0, "weight": "185", "3P": 0.0, "TOV": 1.0, "STL/TOV": 0.0, "TSA": 2.0, "2PA": 2.0, "college": "Duke University", "FG": 0.0, "3PA": 0.0, "DRB": 0.0, "ORB%": 0.0, "BLK%": 0.0, "AST/TOV": 2.0, "position": "PG", "AST": 2.0, "FT%": null, "3PAr": 0.0, "PF": 0.0, "PTS": 0.0, "FGA": 2.0, "DRBr": null, "ORBr": null, "2P": 0.0, "STL": 0.0, "TRB": 0.0, "TOV%": 33.3, "AST%": 22.5, "FTAr": 0.0, "FTA": 0.0, "FIC": -0.5, "eFG%": 0.0, "BLK": 0.0, "birth_date": "1983-03-26", "FG%": 0.0, "2PAr": 1.0, "FTr": 0.0, "+/-": 1.0, "name": "Daniel Ewing", "USG%": 13.7, "DRB%": 0.0, "TS%": 0.0, "experience": 1, "height": 1.9202633504023408, "2P%": 0.0, "MP": 9.483333333333333, "DRtg": 111.0, "ORtg": 35.0, "TRB%": 0.0, "FT/FGA": 0.0, "ORB": 0.0, "3P%": null, "HOB": 0.044444444444444446}}, "scores": {"1": "34", "3": "20", "2": "35", "4": "26", "T": "115"}, "name": "Los Angeles Clippers", "totals": {"STL%": 8.4, "FT": 24.0, "2PA": 78.0, "FG": 45.0, "DRB": 34.0, "ORB%": 30.0, "AST": 31.0, "3PAr": 0.09302325581395349, "PF": 16.0, "FGA": 86.0, "DRBr": 0.7391304347826086, "2P": 44.0, "ORBr": 0.2608695652173913, "TOV%": 9.9, "AST%": 68.9, "FTAr": 0.36046511627906974, "FIC": 107.375, "eFG%": 0.5290697674418605, "FG%": 0.5232558139534884, "2PAr": 0.9069767441860465, "+/-": 19.0, "USG%": 100.0, "DRtg": 100.5, "2P%": 0.5641025641025641, "DRB%": 81.0, "ORtg": 120.4, "TRB%": 56.1, "ORB": 12.0, "3P": 1.0, "TOV": 11.0, "STL/TOV": 0.7272727272727273, "TSA": 99.64, "AST/TOV": 2.8181818181818183, "3PA": 8.0, "BLK%": 15.5, "FT%": 0.7741935483870968, "PTS": 115.0, "HOB": 1.6888888888888889, "STL": 8.0, "TRB": 46.0, "FTA": 31.0, "BLK": 11.0, "FTr": 0.36, "TS%": 0.5770774789241269, "FT/FGA": 0.27906976744186046, "3P%": 0.125}}, "type": "Season"}