{"league": "nba", "code": "200902100MIN", "season": "2008-2009", "away": {"players": {"Jamario Moon": {"STL%": 0.0, "": "us", "FT": 2.0, "weight": "205", "3P": 1.0, "TOV": 2.0, "STL/TOV": 0.0, "TSA": 5.88, "2PA": 4.0, "college": "Meridian Community College", "FG": 4.0, "3PA": 1.0, "DRB": 8.0, "ORB%": 5.1, "BLK%": 0.0, "AST/TOV": 2.0, "position": "SF", "AST": 4.0, "FT%": 1.0, "3PAr": 0.2, "PF": 2.0, "PTS": 11.0, "FGA": 5.0, "DRBr": 0.8888888888888888, "ORBr": 0.1111111111111111, "2P": 3.0, "STL": 0.0, "TRB": 9.0, "TOV%": 25.4, "AST%": 18.7, "FTAr": 0.4, "FTA": 2.0, "FIC": 14.5, "eFG%": 0.9, "BLK": 0.0, "birth_date": "1980-06-13", "FG%": 0.8, "2PAr": 0.8, "FTr": 0.4, "+/-": 21.0, "name": "Jamario Moon", "USG%": 13.2, "DRB%": 28.8, "TS%": 0.935374149659864, "experience": 1, "height": 2.0726652036088757, "2P%": 0.75, "MP": 28.4, "DRtg": 108.0, "ORtg": 145.0, "TRB%": 19.0, "FT/FGA": 0.4, "ORB": 1.0, "3P%": 1.0, "HOB": 0.18604651162790697}, "Jermaine O'Neal": {"STL%": 1.2, "": "us", "FT": 6.0, "weight": "226", "3P": 0.0, "TOV": 4.0, "STL/TOV": 0.25, "TSA": 20.08, "2PA": 17.0, "college": "", "FG": 8.0, "3PA": 0.0, "DRB": 6.0, "ORB%": 7.0, "BLK%": 3.7, "AST/TOV": 0.5, "position": "C", "AST": 2.0, "FT%": 0.8571428571428571, "3PAr": 0.0, "PF": 5.0, "PTS": 22.0, "FGA": 17.0, "DRBr": 0.75, "ORBr": 0.25, "2P": 8.0, "STL": 1.0, "TRB": 8.0, "TOV%": 16.6, "AST%": 6.8, "FTAr": 0.4117647058823529, "FTA": 7.0, "FIC": 11.625, "eFG%": 0.47058823529411764, "BLK": 2.0, "birth_date": "1978-10-13", "FG%": 0.47058823529411764, "2PAr": 1.0, "FTr": 0.412, "+/-": 2.0, "name": "Jermaine O'Neal", "USG%": 27.6, "DRB%": 14.8, "TS%": 0.5478087649402391, "experience": 12, "height": 1.8623506461838577, "2P%": 0.47058823529411764, "MP": 41.53333333333333, "DRtg": 107.0, "ORtg": 99.0, "TRB%": 11.6, "FT/FGA": 0.35294117647058826, "ORB": 2.0, "3P%": null, "HOB": 0.23255813953488372}, "Jose Calderon": {"STL%": 0.0, "": "es", "FT": 4.0, "weight": "200", "3P": 1.0, "TOV": 1.0, "STL/TOV": 0.0, "TSA": 9.76, "2PA": 5.0, "college": "", "FG": 3.0, "3PA": 3.0, "DRB": 3.0, "ORB%": 4.3, "BLK%": 0.0, "AST/TOV": 9.0, "position": "PG", "AST": 9.0, "FT%": 1.0, "3PAr": 0.375, "PF": 0.0, "PTS": 11.0, "FGA": 8.0, "DRBr": 0.75, "ORBr": 0.25, "2P": 2.0, "STL": 0.0, "TRB": 4.0, "TOV%": 9.3, "AST%": 33.2, "FTAr": 0.5, "FTA": 4.0, "FIC": 14.75, "eFG%": 0.4375, "BLK": 0.0, "birth_date": "1981-09-28", "FG%": 0.375, "2PAr": 0.625, "FTr": 0.5, "+/-": 1.0, "name": "Jose Calderon", "USG%": 15.2, "DRB%": 9.1, "TS%": 0.5635245901639344, "experience": 3, "height": 1.9202633504023408, "2P%": 0.4, "MP": 33.61666666666667, "DRtg": 115.0, "ORtg": 133.0, "TRB%": 7.1, "FT/FGA": 0.5, "ORB": 1.0, "3P%": 0.3333333333333333, "HOB": 0.27906976744186046}, "Andrea Bargnani": {"STL%": 0.0, "": "it", "FT": 1.0, "weight": "245", "3P": 1.0, "TOV": 3.0, "STL/TOV": 0.0, "TSA": 17.44, "2PA": 14.0, "college": "", "FG": 8.0, "3PA": 3.0, "DRB": 6.0, "ORB%": 0.0, "BLK%": 2.2, "AST/TOV": 0.6666666666666666, "position": "PF", "AST": 2.0, "FT%": 1.0, "3PAr": 0.17647058823529413, "PF": 1.0, "PTS": 18.0, "FGA": 17.0, "DRBr": 1.0, "ORBr": 0.0, "2P": 7.0, "STL": 0.0, "TRB": 6.0, "TOV%": 14.7, "AST%": 8.3, "FTAr": 0.058823529411764705, "FTA": 1.0, "FIC": 8.875, "eFG%": 0.5, "BLK": 1.0, "birth_date": "1985-10-26", "FG%": 0.47058823529411764, "2PAr": 0.8235294117647058, "FTr": 0.059, "+/-": 4.0, "name": "Andrea Bargnani", "USG%": 27.1, "DRB%": 17.1, "TS%": 0.5160550458715596, "experience": 2, "height": 2.13362594489149, "2P%": 0.5, "MP": 35.88333333333333, "DRtg": 111.0, "ORtg": 88.0, "TRB%": 10.0, "FT/FGA": 0.058823529411764705, "ORB": 0.0, "3P%": 0.3333333333333333, "HOB": 0.23255813953488372}, "Joey Graham": {"STL%": 2.7, "": "us", "FT": 3.0, "weight": "225", "3P": 1.0, "TOV": 0.0, "STL/TOV": null, "TSA": 16.32, "2PA": 14.0, "college": "Oklahoma State University", "FG": 10.0, "3PA": 1.0, "DRB": 6.0, "ORB%": 0.0, "BLK%": 6.1, "AST/TOV": null, "position": "SF", "AST": 2.0, "FT%": 1.0, "3PAr": 0.06666666666666667, "PF": 2.0, "PTS": 24.0, "FGA": 15.0, "DRBr": 1.0, "ORBr": 0.0, "2P": 9.0, "STL": 2.0, "TRB": 6.0, "TOV%": 0.0, "AST%": 8.2, "FTAr": 0.2, "FTA": 3.0, "FIC": 22.125, "eFG%": 0.7, "BLK": 3.0, "birth_date": "1982-06-11", "FG%": 0.6666666666666666, "2PAr": 0.9333333333333333, "FTr": 0.2, "+/-": 3.0, "name": "Joey Graham", "USG%": 20.2, "DRB%": 16.0, "TS%": 0.7352941176470588, "experience": 3, "height": 2.042184832967569, "2P%": 0.6428571428571429, "MP": 38.38333333333333, "DRtg": 102.0, "ORtg": 147.0, "TRB%": 9.4, "FT/FGA": 0.2, "ORB": 0.0, "3P%": 1.0, "HOB": 0.27906976744186046}, "Jason Kapono": {"STL%": 0.0, "": "us", "FT": 1.0, "weight": "213", "3P": 3.0, "TOV": 0.0, "STL/TOV": null, "TSA": 10.44, "2PA": 5.0, "college": "University of California, Los Angeles", "FG": 7.0, "3PA": 5.0, "DRB": 4.0, "ORB%": 0.0, "BLK%": 0.0, "AST/TOV": null, "position": "SG", "AST": 0.0, "FT%": 1.0, "3PAr": 0.5, "PF": 3.0, "PTS": 18.0, "FGA": 10.0, "DRBr": 1.0, "ORBr": 0.0, "2P": 4.0, "STL": 0.0, "TRB": 4.0, "TOV%": 0.0, "AST%": 0.0, "FTAr": 0.1, "FTA": 1.0, "FIC": 11.625, "eFG%": 0.85, "BLK": 0.0, "birth_date": "1981-02-04", "FG%": 0.7, "2PAr": 0.5, "FTr": 0.1, "+/-": 3.0, "name": "Jason Kapono", "USG%": 22.6, "DRB%": 18.6, "TS%": 0.8620689655172414, "experience": 5, "height": 2.0726652036088757, "2P%": 0.8, "MP": 22.016666666666666, "DRtg": 112.0, "ORtg": 158.0, "TRB%": 10.9, "FT/FGA": 0.1, "ORB": 0.0, "3P%": 0.6, "HOB": 0.16279069767441862}, "Roko Ukic": {"STL%": 0.0, "": "hr", "FT": 0.0, "weight": "183", "3P": 0.0, "TOV": 0.0, "STL/TOV": null, "TSA": 3.0, "2PA": 1.0, "college": "", "FG": 1.0, "3PA": 2.0, "DRB": 0.0, "ORB%": 23.1, "BLK%": 0.0, "AST/TOV": null, "position": "PG", "AST": 3.0, "FT%": null, "3PAr": 0.6666666666666666, "PF": 0.0, "PTS": 2.0, "FGA": 3.0, "DRBr": 0.0, "ORBr": 1.0, "2P": 1.0, "STL": 0.0, "TRB": 1.0, "TOV%": 0.0, "AST%": 64.8, "FTAr": 0.0, "FTA": 0.0, "FIC": 3.75, "eFG%": 0.3333333333333333, "BLK": 0.0, "birth_date": "1984-05-12", "FG%": 0.3333333333333333, "2PAr": 0.3333333333333333, "FTr": 0.0, "+/-": 0.0, "name": "Roko Ukic", "USG%": 22.7, "DRB%": 0.0, "TS%": 0.3333333333333333, "experience": 0, "height": 1.9812240916849548, "2P%": 1.0, "MP": 6.283333333333333, "DRtg": 118.0, "ORtg": 119.0, "TRB%": 9.5, "FT/FGA": 0.0, "ORB": 1.0, "3P%": 0.0, "HOB": 0.09302325581395349}, "Anthony Parker": {"STL%": 0.0, "": "us", "FT": 0.0, "weight": "215", "3P": 0.0, "TOV": 1.0, "STL/TOV": 0.0, "TSA": 6.0, "2PA": 5.0, "college": "Bradley University", "FG": 2.0, "3PA": 1.0, "DRB": 3.0, "ORB%": 0.0, "BLK%": 0.0, "AST/TOV": 5.0, "position": "SG", "AST": 5.0, "FT%": null, "3PAr": 0.16666666666666666, "PF": 2.0, "PTS": 4.0, "FGA": 6.0, "DRBr": 1.0, "ORBr": 0.0, "2P": 2.0, "STL": 0.0, "TRB": 3.0, "TOV%": 14.3, "AST%": 20.4, "FTAr": 0.0, "FTA": 0.0, "FIC": 4.75, "eFG%": 0.3333333333333333, "BLK": 0.0, "birth_date": "1975-06-19", "FG%": 0.3333333333333333, "2PAr": 0.8333333333333334, "FTr": 0.0, "+/-": 3.0, "name": "Anthony Parker", "USG%": 11.3, "DRB%": 10.4, "TS%": 0.3333333333333333, "experience": 5, "height": 2.0117044623262617, "2P%": 0.4, "MP": 29.533333333333335, "DRtg": 114.0, "ORtg": 87.0, "TRB%": 6.1, "FT/FGA": 0.0, "ORB": 0.0, "3P%": 0.0, "HOB": 0.16279069767441862}, "Jake Voskuhl": {"STL%": 0.0, "": "us", "FT": 0.0, "weight": "245", "3P": 0.0, "TOV": 1.0, "STL/TOV": 0.0, "TSA": 0.0, "2PA": 0.0, "college": "University of Connecticut", "FG": 0.0, "3PA": 0.0, "DRB": 0.0, "ORB%": 0.0, "BLK%": 0.0, "AST/TOV": 0.0, "position": "C", "AST": 0.0, "FT%": null, "3PAr": null, "PF": 1.0, "PTS": 0.0, "FGA": 0.0, "DRBr": null, "ORBr": null, "2P": 0.0, "STL": 0.0, "TRB": 0.0, "TOV%": 100.0, "AST%": 0.0, "FTAr": null, "FTA": 0.0, "FIC": -1.5, "eFG%": null, "BLK": 0.0, "birth_date": "1977-11-01", "FG%": null, "2PAr": null, "FTr": null, "+/-": 3.0, "name": "Jake Voskuhl", "USG%": 10.9, "DRB%": 0.0, "TS%": null, "experience": 8, "height": 1.8623506461838577, "2P%": null, "MP": 4.35, "DRtg": 117.0, "ORtg": 0.0, "TRB%": 0.0, "FT/FGA": null, "ORB": 0.0, "3P%": null, "HOB": 0.0}}, "scores": {"1": "23", "3": "32", "2": "18", "4": "37", "T": "110"}, "name": "Toronto Raptors", "totals": {"STL%": 3.2, "FT": 17.0, "2PA": 65.0, "FG": 43.0, "DRB": 36.0, "ORB%": 15.2, "AST": 27.0, "3PAr": 0.19753086419753085, "PF": 16.0, "FGA": 81.0, "DRBr": 0.8780487804878049, "2P": 36.0, "ORBr": 0.12195121951219512, "TOV%": 11.9, "AST%": 62.8, "FTAr": 0.2222222222222222, "FIC": 90.5, "eFG%": 0.5740740740740741, "FG%": 0.5308641975308642, "2PAr": 0.8024691358024691, "+/-": 8.0, "USG%": 100.0, "DRtg": 109.4, "2P%": 0.5538461538461539, "DRB%": 76.6, "ORtg": 118.0, "TRB%": 51.3, "ORB": 5.0, "3P": 7.0, "TOV": 12.0, "STL/TOV": 0.25, "TSA": 88.92, "AST/TOV": 2.25, "3PA": 16.0, "BLK%": 9.7, "FT%": 0.9444444444444444, "PTS": 110.0, "HOB": 1.627906976744186, "STL": 3.0, "TRB": 41.0, "FTA": 18.0, "BLK": 6.0, "FTr": 0.222, "TS%": 0.6185335132703553, "FT/FGA": 0.20987654320987653, "3P%": 0.4375}}, "time": "19:00:00", "country": "United States", "date": "2009-02-10", "home": {"players": {"Ryan Gomes": {"STL%": 0.0, "": "us", "FT": 2.0, "weight": "250", "3P": 1.0, "TOV": 1.0, "STL/TOV": 0.0, "TSA": 17.88, "2PA": 11.0, "college": "Providence College", "FG": 7.0, "3PA": 6.0, "DRB": 4.0, "ORB%": 2.9, "BLK%": 0.0, "AST/TOV": 2.0, "position": "SF", "AST": 2.0, "FT%": 1.0, "3PAr": 0.35294117647058826, "PF": 2.0, "PTS": 17.0, "FGA": 17.0, "DRBr": 0.8, "ORBr": 0.2, "2P": 6.0, "STL": 0.0, "TRB": 5.0, "TOV%": 5.3, "AST%": 9.8, "FTAr": 0.11764705882352941, "FTA": 2.0, "FIC": 7.5, "eFG%": 0.4411764705882353, "BLK": 0.0, "birth_date": "1982-09-01", "FG%": 0.4117647058823529, "2PAr": 0.6470588235294118, "FTr": 0.118, "+/-": 0.0, "name": "Ryan Gomes", "USG%": 24.6, "DRB%": 16.7, "TS%": 0.4753914988814318, "experience": 3, "height": 2.042184832967569, "2P%": 0.5454545454545454, "MP": 34.75, "DRtg": 120.0, "ORtg": 102.0, "TRB%": 8.6, "FT/FGA": 0.11764705882352941, "ORB": 1.0, "3P%": 0.16666666666666666, "HOB": 0.23684210526315788}, "Rodney Carney": {"STL%": 0.0, "": "us", "FT": 3.0, "weight": "205", "3P": 1.0, "TOV": 1.0, "STL/TOV": 0.0, "TSA": 12.76, "2PA": 6.0, "college": "University of Memphis", "FG": 4.0, "3PA": 5.0, "DRB": 2.0, "ORB%": 9.1, "BLK%": 0.0, "AST/TOV": 1.0, "position": "SG", "AST": 1.0, "FT%": 0.75, "3PAr": 0.45454545454545453, "PF": 1.0, "PTS": 12.0, "FGA": 11.0, "DRBr": 0.5, "ORBr": 0.5, "2P": 3.0, "STL": 0.0, "TRB": 4.0, "TOV%": 7.3, "AST%": 7.3, "FTAr": 0.36363636363636365, "FTA": 4.0, "FIC": 5.25, "eFG%": 0.4090909090909091, "BLK": 0.0, "birth_date": "1984-04-15", "FG%": 0.36363636363636365, "2PAr": 0.5454545454545454, "FTr": 0.364, "+/-": -16.0, "name": "Rodney Carney", "USG%": 27.8, "DRB%": 13.0, "TS%": 0.4702194357366771, "experience": 2, "height": 2.042184832967569, "2P%": 0.5, "MP": 22.35, "DRtg": 120.0, "ORtg": 103.0, "TRB%": 10.7, "FT/FGA": 0.2727272727272727, "ORB": 2.0, "3P%": 0.2, "HOB": 0.13157894736842105}, "Brian Cardinal": {"STL%": 0.0, "": "us", "FT": 0.0, "weight": "245", "3P": 0.0, "TOV": 1.0, "STL/TOV": 0.0, "TSA": 3.0, "2PA": 1.0, "college": "Purdue University", "FG": 1.0, "3PA": 2.0, "DRB": 2.0, "ORB%": 7.2, "BLK%": 5.2, "AST/TOV": 1.0, "position": "PF", "AST": 1.0, "FT%": null, "3PAr": 0.6666666666666666, "PF": 1.0, "PTS": 2.0, "FGA": 3.0, "DRBr": 0.6666666666666666, "ORBr": 0.3333333333333333, "2P": 1.0, "STL": 0.0, "TRB": 3.0, "TOV%": 25.0, "AST%": 9.8, "FTAr": 0.0, "FTA": 0.0, "FIC": 2.75, "eFG%": 0.3333333333333333, "BLK": 1.0, "birth_date": "1977-05-02", "FG%": 0.3333333333333333, "2PAr": 0.3333333333333333, "FTr": 0.0, "+/-": -10.0, "name": "Brian Cardinal", "USG%": 12.8, "DRB%": 20.5, "TS%": 0.3333333333333333, "experience": 8, "height": 2.0726652036088757, "2P%": 1.0, "MP": 14.166666666666666, "DRtg": 114.0, "ORtg": 75.0, "TRB%": 12.7, "FT/FGA": 0.0, "ORB": 1.0, "3P%": 0.0, "HOB": 0.05263157894736842}, "Kevin Love": {"STL%": 1.4, "": "us", "FT": 3.0, "weight": "251", "3P": 0.0, "TOV": 0.0, "STL/TOV": null, "TSA": 15.76, "2PA": 14.0, "college": "University of California, Los Angeles", "FG": 6.0, "3PA": 0.0, "DRB": 7.0, "ORB%": 13.4, "BLK%": 1.9, "AST/TOV": null, "position": "C", "AST": 0.0, "FT%": 0.75, "3PAr": 0.0, "PF": 3.0, "PTS": 15.0, "FGA": 14.0, "DRBr": 0.5833333333333334, "ORBr": 0.4166666666666667, "2P": 6.0, "STL": 1.0, "TRB": 12.0, "TOV%": 0.0, "AST%": 0.0, "FTAr": 0.2857142857142857, "FTA": 4.0, "FIC": 13.75, "eFG%": 0.42857142857142855, "BLK": 1.0, "birth_date": "1988-09-07", "FG%": 0.42857142857142855, "2PAr": 1.0, "FTr": 0.286, "+/-": -4.0, "name": "Kevin Love", "USG%": 18.8, "DRB%": 26.8, "TS%": 0.47588832487309646, "experience": 0, "height": 1.8593026091197267, "2P%": 0.42857142857142855, "MP": 38.0, "DRtg": 114.0, "ORtg": 116.0, "TRB%": 18.9, "FT/FGA": 0.21428571428571427, "ORB": 5.0, "3P%": null, "HOB": 0.15789473684210525}, "Sebastian Telfair": {"STL%": 0.0, "": "us", "FT": 1.0, "weight": "165", "3P": 0.0, "TOV": 2.0, "STL/TOV": 0.0, "TSA": 12.88, "2PA": 10.0, "college": "", "FG": 5.0, "3PA": 2.0, "DRB": 1.0, "ORB%": 0.0, "BLK%": 0.0, "AST/TOV": 1.5, "position": "PG", "AST": 3.0, "FT%": 0.5, "3PAr": 0.16666666666666666, "PF": 5.0, "PTS": 11.0, "FGA": 12.0, "DRBr": 1.0, "ORBr": 0.0, "2P": 5.0, "STL": 0.0, "TRB": 1.0, "TOV%": 13.4, "AST%": 11.8, "FTAr": 0.16666666666666666, "FTA": 2.0, "FIC": 0.5, "eFG%": 0.4166666666666667, "BLK": 0.0, "birth_date": "1985-06-09", "FG%": 0.4166666666666667, "2PAr": 0.8333333333333334, "FTr": 0.167, "+/-": -8.0, "name": "Sebastian Telfair", "USG%": 17.5, "DRB%": 3.8, "TS%": 0.42701863354037267, "experience": 4, "height": 1.8288222384784198, "2P%": 0.5, "MP": 38.36666666666667, "DRtg": 121.0, "ORtg": 85.0, "TRB%": 1.6, "FT/FGA": 0.08333333333333333, "ORB": 0.0, "3P%": 0.0, "HOB": 0.21052631578947367}, "Randy Foye": {"STL%": 1.3, "": "us", "FT": 8.0, "weight": "213", "3P": 3.0, "TOV": 1.0, "STL/TOV": 1.0, "TSA": 25.52, "2PA": 16.0, "college": "Villanova University", "FG": 11.0, "3PA": 6.0, "DRB": 8.0, "ORB%": 0.0, "BLK%": 1.9, "AST/TOV": 2.0, "position": "SG", "AST": 2.0, "FT%": 1.0, "3PAr": 0.2727272727272727, "PF": 2.0, "PTS": 33.0, "FGA": 22.0, "DRBr": 1.0, "ORBr": 0.0, "2P": 8.0, "STL": 1.0, "TRB": 8.0, "TOV%": 3.8, "AST%": 9.8, "FTAr": 0.36363636363636365, "FTA": 8.0, "FIC": 21.5, "eFG%": 0.5681818181818182, "BLK": 1.0, "birth_date": "1983-09-24", "FG%": 0.5, "2PAr": 0.7272727272727273, "FTr": 0.364, "+/-": 1.0, "name": "Randy Foye", "USG%": 30.2, "DRB%": 29.3, "TS%": 0.646551724137931, "experience": 2, "height": 1.9507437210436478, "2P%": 0.5, "MP": 39.733333333333334, "DRtg": 114.0, "ORtg": 133.0, "TRB%": 12.1, "FT/FGA": 0.36363636363636365, "ORB": 0.0, "3P%": 0.5, "HOB": 0.34210526315789475}, "Mike Miller": {"STL%": 0.0, "": "us", "FT": 2.0, "weight": "218", "3P": 2.0, "TOV": 1.0, "STL/TOV": 0.0, "TSA": 10.32, "2PA": 3.0, "college": "University of Florida", "FG": 4.0, "3PA": 6.0, "DRB": 2.0, "ORB%": 2.3, "BLK%": 0.0, "AST/TOV": 5.0, "position": "SF", "AST": 5.0, "FT%": 0.6666666666666666, "3PAr": 0.6666666666666666, "PF": 2.0, "PTS": 12.0, "FGA": 9.0, "DRBr": 0.6666666666666666, "ORBr": 0.3333333333333333, "2P": 2.0, "STL": 0.0, "TRB": 3.0, "TOV%": 8.8, "AST%": 16.4, "FTAr": 0.3333333333333333, "FTA": 3.0, "FIC": 9.625, "eFG%": 0.5555555555555556, "BLK": 0.0, "birth_date": "1980-02-19", "FG%": 0.4444444444444444, "2PAr": 0.3333333333333333, "FTr": 0.333, "+/-": -1.0, "name": "Mike Miller", "USG%": 11.8, "DRB%": 6.7, "TS%": 0.5813953488372093, "experience": 8, "height": 2.0726652036088757, "2P%": 0.6666666666666666, "MP": 43.55, "DRtg": 121.0, "ORtg": 125.0, "TRB%": 4.1, "FT/FGA": 0.2222222222222222, "ORB": 1.0, "3P%": 0.3333333333333333, "HOB": 0.23684210526315788}, "Jason Collins": {"STL%": 0.0, "": "us", "FT": 0.0, "weight": "255", "3P": 0.0, "TOV": 0.0, "STL/TOV": null, "TSA": 1.0, "2PA": 1.0, "college": "Stanford University", "FG": 0.0, "3PA": 0.0, "DRB": 2.0, "ORB%": 11.2, "BLK%": 0.0, "AST/TOV": null, "position": "C", "AST": 0.0, "FT%": null, "3PAr": 0.0, "PF": 1.0, "PTS": 0.0, "FGA": 1.0, "DRBr": 0.6666666666666666, "ORBr": 0.3333333333333333, "2P": 0.0, "STL": 0.0, "TRB": 3.0, "TOV%": 0.0, "AST%": 0.0, "FTAr": 0.0, "FTA": 0.0, "FIC": 1.25, "eFG%": 0.0, "BLK": 0.0, "birth_date": "1978-12-02", "FG%": 0.0, "2PAr": 1.0, "FTr": 0.0, "+/-": -2.0, "name": "Jason Collins", "USG%": 5.0, "DRB%": 32.0, "TS%": 0.0, "experience": 7, "height": 2.13362594489149, "2P%": 0.0, "MP": 9.1, "DRtg": 118.0, "ORtg": 66.0, "TRB%": 19.8, "FT/FGA": 0.0, "ORB": 1.0, "3P%": null, "HOB": 0.0}}, "scores": {"1": "16", "3": "32", "2": "32", "4": "22", "T": "102"}, "name": "Minnesota Timberwolves", "totals": {"STL%": 2.1, "FT": 19.0, "2PA": 62.0, "FG": 38.0, "DRB": 28.0, "ORB%": 23.4, "AST": 14.0, "3PAr": 0.30337078651685395, "PF": 17.0, "FGA": 89.0, "DRBr": 0.717948717948718, "2P": 31.0, "ORBr": 0.28205128205128205, "TOV%": 6.6, "AST%": 36.8, "FTAr": 0.25842696629213485, "FIC": 62.125, "eFG%": 0.46629213483146065, "FG%": 0.42696629213483145, "2PAr": 0.6966292134831461, "+/-": -8.0, "USG%": 100.0, "DRtg": 118.0, "2P%": 0.5, "DRB%": 84.8, "ORtg": 109.4, "TRB%": 48.8, "ORB": 11.0, "3P": 7.0, "TOV": 7.0, "STL/TOV": 0.2857142857142857, "TSA": 99.12, "AST/TOV": 2.0, "3PA": 27.0, "BLK%": 4.6, "FT%": 0.8260869565217391, "PTS": 102.0, "HOB": 1.368421052631579, "STL": 2.0, "TRB": 39.0, "FTA": 23.0, "BLK": 3.0, "FTr": 0.258, "TS%": 0.5145278450363195, "FT/FGA": 0.21348314606741572, "3P%": 0.25925925925925924}}, "type": "Season"}