{"league": "nba", "code": "201101220NOH", "season": "2010-2011", "away": {"players": {"Tim Duncan": {"STL%": 2.5, "": "vi", "FT": 2.0, "weight": "250", "3P": 0.0, "TOV": 0.0, "STL/TOV": null, "TSA": 11.88, "2PA": 11.0, "college": "Wake Forest University", "FG": 2.0, "3PA": 0.0, "DRB": 5.0, "ORB%": 0.0, "BLK%": 0.0, "AST/TOV": null, "position": "C", "AST": 3.0, "FT%": 1.0, "3PAr": 0.0, "PF": 1.0, "PTS": 6.0, "FGA": 11.0, "DRBr": 1.0, "ORBr": 0.0, "2P": 2.0, "STL": 1.0, "TRB": 5.0, "TOV%": 0.0, "AST%": 30.5, "FTAr": 0.18181818181818182, "FTA": 2.0, "FIC": 4.25, "eFG%": 0.18181818181818182, "BLK": 0.0, "birth_date": "1976-04-25", "FG%": 0.18181818181818182, "2PAr": 1.0, "FTr": 0.182, "+/-": -15.0, "name": "Tim Duncan", "USG%": 27.6, "DRB%": 25.1, "TS%": 0.2525252525252525, "experience": 13, "height": 1.8623506461838577, "2P%": 0.18181818181818182, "MP": 22.733333333333334, "DRtg": 106.0, "ORtg": 62.0, "TRB%": 11.9, "FT/FGA": 0.18181818181818182, "ORB": 0.0, "3P%": null, "HOB": 0.2}, "DeJuan Blair": {"STL%": 2.0, "": "us", "FT": 1.0, "weight": "270", "3P": 0.0, "TOV": 0.0, "STL/TOV": null, "TSA": 7.32, "2PA": 6.0, "college": "University of Pittsburgh", "FG": 3.0, "3PA": 0.0, "DRB": 5.0, "ORB%": 3.7, "BLK%": 0.0, "AST/TOV": null, "position": "PF", "AST": 0.0, "FT%": 0.3333333333333333, "3PAr": 0.0, "PF": 4.0, "PTS": 7.0, "FGA": 6.0, "DRBr": 0.8333333333333334, "ORBr": 0.16666666666666666, "2P": 3.0, "STL": 1.0, "TRB": 6.0, "TOV%": 0.0, "AST%": 0.0, "FTAr": 0.5, "FTA": 3.0, "FIC": 5.125, "eFG%": 0.5, "BLK": 0.0, "birth_date": "1989-04-22", "FG%": 0.5, "2PAr": 1.0, "FTr": 0.5, "+/-": -8.0, "name": "DeJuan Blair", "USG%": 13.9, "DRB%": 20.6, "TS%": 0.4781420765027322, "experience": 1, "height": 2.042184832967569, "2P%": 0.5, "MP": 27.783333333333335, "DRtg": 109.0, "ORtg": 97.0, "TRB%": 11.6, "FT/FGA": 0.16666666666666666, "ORB": 1.0, "3P%": null, "HOB": 0.12}, "Tony Parker": {"STL%": 0.0, "": "be", "FT": 2.0, "weight": "185", "3P": 0.0, "TOV": 1.0, "STL/TOV": 0.0, "TSA": 8.88, "2PA": 7.0, "college": "", "FG": 4.0, "3PA": 1.0, "DRB": 1.0, "ORB%": 4.1, "BLK%": 0.0, "AST/TOV": 0.0, "position": "PG", "AST": 0.0, "FT%": 1.0, "3PAr": 0.125, "PF": 3.0, "PTS": 10.0, "FGA": 8.0, "DRBr": 0.5, "ORBr": 0.5, "2P": 4.0, "STL": 0.0, "TRB": 2.0, "TOV%": 10.1, "AST%": 0.0, "FTAr": 0.25, "FTA": 2.0, "FIC": 2.5, "eFG%": 0.5, "BLK": 0.0, "birth_date": "1982-05-17", "FG%": 0.5, "2PAr": 0.875, "FTr": 0.25, "+/-": -29.0, "name": "Tony Parker", "USG%": 20.8, "DRB%": 4.6, "TS%": 0.563063063063063, "experience": 9, "height": 1.889782979761034, "2P%": 0.5714285714285714, "MP": 25.05, "DRtg": 120.0, "ORtg": 100.0, "TRB%": 4.3, "FT/FGA": 0.25, "ORB": 1.0, "3P%": 0.0, "HOB": 0.16}, "George Hill": {"STL%": 2.9, "": "us", "FT": 3.0, "weight": "188", "3P": 1.0, "TOV": 1.0, "STL/TOV": 1.0, "TSA": 7.76, "2PA": 3.0, "college": "Indiana University-Purdue University Indianapolis", "FG": 2.0, "3PA": 3.0, "DRB": 1.0, "ORB%": 0.0, "BLK%": 0.0, "AST/TOV": 0.0, "position": "PG", "AST": 0.0, "FT%": 0.75, "3PAr": 0.5, "PF": 0.0, "PTS": 8.0, "FGA": 6.0, "DRBr": 1.0, "ORBr": 0.0, "2P": 1.0, "STL": 1.0, "TRB": 1.0, "TOV%": 11.4, "AST%": 0.0, "FTAr": 0.6666666666666666, "FTA": 4.0, "FIC": 2.75, "eFG%": 0.4166666666666667, "BLK": 0.0, "birth_date": "1986-05-04", "FG%": 0.3333333333333333, "2PAr": 0.5, "FTr": 0.667, "+/-": -11.0, "name": "George Hill", "USG%": 23.8, "DRB%": 5.9, "TS%": 0.5154639175257733, "experience": 2, "height": 1.9202633504023408, "2P%": 0.3333333333333333, "MP": 19.416666666666668, "DRtg": 114.0, "ORtg": 90.0, "TRB%": 2.8, "FT/FGA": 0.5, "ORB": 0.0, "3P%": 0.3333333333333333, "HOB": 0.08}, "Chris Quinn": {"STL%": 0.0, "": "us", "FT": 0.0, "weight": "185", "3P": 0.0, "TOV": 0.0, "STL/TOV": null, "TSA": 4.0, "2PA": 3.0, "college": "University of Notre Dame", "FG": 2.0, "3PA": 1.0, "DRB": 0.0, "ORB%": 0.0, "BLK%": 0.0, "AST/TOV": null, "position": "PG", "AST": 1.0, "FT%": null, "3PAr": 0.25, "PF": 1.0, "PTS": 4.0, "FGA": 4.0, "DRBr": null, "ORBr": null, "2P": 2.0, "STL": 0.0, "TRB": 0.0, "TOV%": 0.0, "AST%": 18.5, "FTAr": 0.0, "FTA": 0.0, "FIC": 1.5, "eFG%": 0.5, "BLK": 0.0, "birth_date": "1983-09-27", "FG%": 0.5, "2PAr": 0.75, "FTr": 0.0, "+/-": -1.0, "name": "Chris Quinn", "USG%": 14.8, "DRB%": 0.0, "TS%": 0.5, "experience": 4, "height": 1.889782979761034, "2P%": 0.6666666666666666, "MP": 14.216666666666667, "DRtg": 123.0, "ORtg": 101.0, "TRB%": 0.0, "FT/FGA": 0.0, "ORB": 0.0, "3P%": 0.0, "HOB": 0.12}, "Richard Jefferson": {"STL%": 0.0, "": "us", "FT": 2.0, "weight": "233", "3P": 1.0, "TOV": 3.0, "STL/TOV": 0.0, "TSA": 8.88, "2PA": 5.0, "college": "University of Arizona", "FG": 3.0, "3PA": 3.0, "DRB": 3.0, "ORB%": 3.6, "BLK%": 0.0, "AST/TOV": 0.3333333333333333, "position": "SF", "AST": 1.0, "FT%": 1.0, "3PAr": 0.375, "PF": 3.0, "PTS": 9.0, "FGA": 8.0, "DRBr": 0.75, "ORBr": 0.25, "2P": 2.0, "STL": 0.0, "TRB": 4.0, "TOV%": 25.3, "AST%": 8.5, "FTAr": 0.25, "FTA": 2.0, "FIC": 2.0, "eFG%": 0.4375, "BLK": 0.0, "birth_date": "1980-06-21", "FG%": 0.375, "2PAr": 0.625, "FTr": 0.25, "+/-": -24.0, "name": "Richard Jefferson", "USG%": 22.1, "DRB%": 12.1, "TS%": 0.5067567567567567, "experience": 9, "height": 2.042184832967569, "2P%": 0.4, "MP": 28.3, "DRtg": 117.0, "ORtg": 78.0, "TRB%": 7.6, "FT/FGA": 0.25, "ORB": 1.0, "3P%": 0.3333333333333333, "HOB": 0.16}, "Antonio McDyess": {"STL%": 0.0, "": "us", "FT": 0.0, "weight": "220", "3P": 0.0, "TOV": 0.0, "STL/TOV": null, "TSA": 2.0, "2PA": 2.0, "college": "University of Alabama", "FG": 0.0, "3PA": 0.0, "DRB": 2.0, "ORB%": 8.3, "BLK%": 0.0, "AST/TOV": null, "position": "PF", "AST": 1.0, "FT%": null, "3PAr": 0.0, "PF": 0.0, "PTS": 0.0, "FGA": 2.0, "DRBr": 0.6666666666666666, "ORBr": 0.3333333333333333, "2P": 0.0, "STL": 0.0, "TRB": 3.0, "TOV%": 0.0, "AST%": 15.7, "FTAr": 0.0, "FTA": 0.0, "FIC": 2.0, "eFG%": 0.0, "BLK": 0.0, "birth_date": "1974-09-07", "FG%": 0.0, "2PAr": 1.0, "FTr": 0.0, "+/-": -5.0, "name": "Antonio McDyess", "USG%": 8.6, "DRB%": 18.7, "TS%": 0.0, "experience": 14, "height": 2.103145574250183, "2P%": 0.0, "MP": 12.233333333333333, "DRtg": 115.0, "ORtg": 48.0, "TRB%": 13.2, "FT/FGA": 0.0, "ORB": 1.0, "3P%": null, "HOB": 0.04}, "Gary Neal": {"STL%": 0.0, "": "us", "FT": 0.0, "weight": "210", "3P": 2.0, "TOV": 1.0, "STL/TOV": 0.0, "TSA": 9.0, "2PA": 4.0, "college": "Towson University", "FG": 3.0, "3PA": 5.0, "DRB": 1.0, "ORB%": 0.0, "BLK%": 0.0, "AST/TOV": 2.0, "position": "SG", "AST": 2.0, "FT%": null, "3PAr": 0.5555555555555556, "PF": 0.0, "PTS": 8.0, "FGA": 9.0, "DRBr": 1.0, "ORBr": 0.0, "2P": 1.0, "STL": 0.0, "TRB": 1.0, "TOV%": 10.0, "AST%": 15.5, "FTAr": 0.0, "FTA": 0.0, "FIC": 3.0, "eFG%": 0.4444444444444444, "BLK": 0.0, "birth_date": "1984-10-03", "FG%": 0.3333333333333333, "2PAr": 0.4444444444444444, "FTr": 0.0, "+/-": -7.0, "name": "Gary Neal", "USG%": 17.3, "DRB%": 3.7, "TS%": 0.4444444444444444, "experience": 0, "height": 1.9507437210436478, "2P%": 0.25, "MP": 30.516666666666666, "DRtg": 122.0, "ORtg": 81.0, "TRB%": 1.8, "FT/FGA": 0.0, "ORB": 0.0, "3P%": 0.4, "HOB": 0.2}, "Larry Owens": {"STL%": 4.6, "": "us", "FT": 1.0, "weight": "210", "3P": 0.0, "TOV": 0.0, "STL/TOV": null, "TSA": 2.88, "2PA": 2.0, "college": "Oral Roberts University", "FG": 2.0, "3PA": 0.0, "DRB": 2.0, "ORB%": 0.0, "BLK%": 0.0, "AST/TOV": null, "position": "SF", "AST": 0.0, "FT%": 0.5, "3PAr": 0.0, "PF": 1.0, "PTS": 5.0, "FGA": 2.0, "DRBr": 1.0, "ORBr": 0.0, "2P": 2.0, "STL": 1.0, "TRB": 2.0, "TOV%": 0.0, "AST%": 0.0, "FTAr": 1.0, "FTA": 2.0, "FIC": 4.75, "eFG%": 1.0, "BLK": 0.0, "birth_date": "1983-01-08", "FG%": 1.0, "2PAr": 1.0, "FTr": 1.0, "+/-": 0.0, "name": "Larry Owens", "USG%": 12.3, "DRB%": 18.6, "TS%": 0.8680555555555556, "experience": 0, "height": 2.042184832967569, "2P%": 1.0, "MP": 12.316666666666666, "DRtg": 104.0, "ORtg": 169.0, "TRB%": 8.8, "FT/FGA": 0.5, "ORB": 0.0, "3P%": null, "HOB": 0.08}, "Tiago Splitter": {"STL%": 2.3, "": "br", "FT": 7.0, "weight": "245", "3P": 0.0, "TOV": 1.0, "STL/TOV": 1.0, "TSA": 9.4, "2PA": 5.0, "college": "", "FG": 2.0, "3PA": 0.0, "DRB": 5.0, "ORB%": 4.0, "BLK%": 0.0, "AST/TOV": 1.0, "position": "C", "AST": 1.0, "FT%": 0.7, "3PAr": 0.0, "PF": 3.0, "PTS": 11.0, "FGA": 5.0, "DRBr": 0.8333333333333334, "ORBr": 0.16666666666666666, "2P": 2.0, "STL": 1.0, "TRB": 6.0, "TOV%": 9.6, "AST%": 9.0, "FTAr": 2.0, "FTA": 10.0, "FIC": 7.75, "eFG%": 0.4, "BLK": 0.0, "birth_date": "1985-01-01", "FG%": 0.4, "2PAr": 1.0, "FTr": 2.0, "+/-": -9.0, "name": "Tiago Splitter", "USG%": 21.7, "DRB%": 22.6, "TS%": 0.5851063829787234, "experience": 0, "height": 1.8623506461838577, "2P%": 0.4, "MP": 25.266666666666666, "DRtg": 107.0, "ORtg": 115.0, "TRB%": 12.8, "FT/FGA": 1.4, "ORB": 1.0, "3P%": null, "HOB": 0.12}, "Manu Ginobili": {"STL%": 2.6, "": "ar", "FT": 0.0, "weight": "205", "3P": 0.0, "TOV": 4.0, "STL/TOV": 0.25, "TSA": 8.0, "2PA": 6.0, "college": "", "FG": 2.0, "3PA": 2.0, "DRB": 2.0, "ORB%": 0.0, "BLK%": 0.0, "AST/TOV": 1.5, "position": "SG", "AST": 6.0, "FT%": null, "3PAr": 0.25, "PF": 1.0, "PTS": 4.0, "FGA": 8.0, "DRBr": 1.0, "ORBr": 0.0, "2P": 2.0, "STL": 1.0, "TRB": 2.0, "TOV%": 33.3, "AST%": 62.9, "FTAr": 0.0, "FTA": 0.0, "FIC": 2.0, "eFG%": 0.25, "BLK": 0.0, "birth_date": "1977-07-28", "FG%": 0.25, "2PAr": 0.75, "FTr": 0.0, "+/-": -11.0, "name": "Manu Ginobili", "USG%": 28.6, "DRB%": 10.3, "TS%": 0.25, "experience": 8, "height": 2.0117044623262617, "2P%": 0.3333333333333333, "MP": 22.166666666666668, "DRtg": 113.0, "ORtg": 51.0, "TRB%": 4.9, "FT/FGA": 0.0, "ORB": 0.0, "3P%": 0.0, "HOB": 0.32}}, "scores": {"1": "12", "3": "10", "2": "26", "4": "24", "T": "72"}, "name": "San Antonio Spurs", "totals": {"STL%": 7.1, "FT": 18.0, "2PA": 54.0, "FG": 25.0, "DRB": 27.0, "ORB%": 10.6, "AST": 15.0, "3PAr": 0.21739130434782608, "PF": 17.0, "FGA": 69.0, "DRBr": 0.84375, "2P": 21.0, "ORBr": 0.15625, "TOV%": 12.1, "AST%": 60.0, "FTAr": 0.36231884057971014, "FIC": 37.625, "eFG%": 0.391304347826087, "FG%": 0.36231884057971014, "2PAr": 0.782608695652174, "+/-": -24.0, "USG%": 100.0, "DRtg": 113.9, "2P%": 0.3888888888888889, "DRB%": 64.3, "ORtg": 85.4, "TRB%": 36.0, "ORB": 5.0, "3P": 4.0, "TOV": 11.0, "STL/TOV": 0.5454545454545454, "TSA": 80.0, "AST/TOV": 1.3636363636363635, "3PA": 15.0, "BLK%": 0.0, "FT%": 0.72, "PTS": 72.0, "HOB": 1.6, "STL": 6.0, "TRB": 32.0, "FTA": 25.0, "BLK": 0.0, "FTr": 0.362, "TS%": 0.45, "FT/FGA": 0.2608695652173913, "3P%": 0.26666666666666666}}, "time": "19:00:00", "country": "United States", "date": "2011-01-22", "home": {"players": {"David West": {"STL%": 3.8, "": "us", "FT": 2.0, "weight": "250", "3P": 0.0, "TOV": 4.0, "STL/TOV": 0.5, "TSA": 11.88, "2PA": 11.0, "college": "Xavier University", "FG": 8.0, "3PA": 0.0, "DRB": 4.0, "ORB%": 23.0, "BLK%": 3.0, "AST/TOV": 0.75, "position": "PF", "AST": 3.0, "FT%": 1.0, "3PAr": 0.0, "PF": 1.0, "PTS": 18.0, "FGA": 11.0, "DRBr": 0.4, "ORBr": 0.6, "2P": 8.0, "STL": 2.0, "TRB": 10.0, "TOV%": 25.2, "AST%": 19.3, "FTAr": 0.18181818181818182, "FTA": 2.0, "FIC": 19.5, "eFG%": 0.7272727272727273, "BLK": 1.0, "birth_date": "1980-08-29", "FG%": 0.7272727272727273, "2PAr": 1.0, "FTr": 0.182, "+/-": 24.0, "name": "David West", "USG%": 25.5, "DRB%": 13.7, "TS%": 0.7575757575757576, "experience": 7, "height": 2.103145574250183, "2P%": 0.7272727272727273, "MP": 29.766666666666666, "DRtg": 82.0, "ORtg": 127.0, "TRB%": 18.1, "FT/FGA": 0.18181818181818182, "ORB": 6.0, "3P%": null, "HOB": 0.2894736842105263}, "Willie Green": {"STL%": 0.0, "": "us", "FT": 0.0, "weight": "200", "3P": 0.0, "TOV": 0.0, "STL/TOV": null, "TSA": 2.0, "2PA": 2.0, "college": "University of Detroit Mercy", "FG": 0.0, "3PA": 0.0, "DRB": 1.0, "ORB%": 0.0, "BLK%": 0.0, "AST/TOV": null, "position": "SG", "AST": 1.0, "FT%": null, "3PAr": 0.0, "PF": 1.0, "PTS": 0.0, "FGA": 2.0, "DRBr": 1.0, "ORBr": 0.0, "2P": 0.0, "STL": 0.0, "TRB": 1.0, "TOV%": 0.0, "AST%": 11.9, "FTAr": 0.0, "FTA": 0.0, "FIC": -0.25, "eFG%": 0.0, "BLK": 0.0, "birth_date": "1981-07-28", "FG%": 0.0, "2PAr": 1.0, "FTr": 0.0, "+/-": 7.0, "name": "Willie Green", "USG%": 9.0, "DRB%": 9.6, "TS%": 0.0, "experience": 7, "height": 1.9507437210436478, "2P%": 0.0, "MP": 10.6, "DRtg": 94.0, "ORtg": 40.0, "TRB%": 5.1, "FT/FGA": 0.0, "ORB": 0.0, "3P%": null, "HOB": 0.02631578947368421}, "Marco Belinelli": {"STL%": 0.0, "": "it", "FT": 1.0, "weight": "210", "3P": 2.0, "TOV": 1.0, "STL/TOV": 0.0, "TSA": 10.88, "2PA": 5.0, "college": "", "FG": 2.0, "3PA": 5.0, "DRB": 1.0, "ORB%": 0.0, "BLK%": 0.0, "AST/TOV": 4.0, "position": "SG", "AST": 4.0, "FT%": 0.5, "3PAr": 0.5, "PF": 3.0, "PTS": 7.0, "FGA": 10.0, "DRBr": 1.0, "ORBr": 0.0, "2P": 0.0, "STL": 0.0, "TRB": 1.0, "TOV%": 8.4, "AST%": 27.8, "FTAr": 0.2, "FTA": 2.0, "FIC": 1.0, "eFG%": 0.3, "BLK": 0.0, "birth_date": "1986-03-25", "FG%": 0.2, "2PAr": 0.5, "FTr": 0.2, "+/-": 29.0, "name": "Marco Belinelli", "USG%": 27.4, "DRB%": 4.9, "TS%": 0.3216911764705882, "experience": 3, "height": 1.9812240916849548, "2P%": 0.0, "MP": 20.716666666666665, "DRtg": 94.0, "ORtg": 90.0, "TRB%": 2.6, "FT/FGA": 0.1, "ORB": 0.0, "3P%": 0.4, "HOB": 0.15789473684210525}, "Quincy Pondexter": {"STL%": 0.0, "": "us", "FT": 0.0, "weight": "220", "3P": 1.0, "TOV": 1.0, "STL/TOV": 0.0, "TSA": 7.0, "2PA": 6.0, "college": "University of Washington", "FG": 3.0, "3PA": 1.0, "DRB": 1.0, "ORB%": 0.0, "BLK%": 0.0, "AST/TOV": 1.0, "position": "SF", "AST": 1.0, "FT%": null, "3PAr": 0.14285714285714285, "PF": 4.0, "PTS": 7.0, "FGA": 7.0, "DRBr": 1.0, "ORBr": 0.0, "2P": 2.0, "STL": 0.0, "TRB": 1.0, "TOV%": 12.5, "AST%": 11.8, "FTAr": 0.0, "FTA": 0.0, "FIC": 0.5, "eFG%": 0.5, "BLK": 0.0, "birth_date": "1988-03-10", "FG%": 0.42857142857142855, "2PAr": 0.8571428571428571, "FTr": 0.0, "+/-": -2.0, "name": "Quincy Pondexter", "USG%": 26.4, "DRB%": 7.1, "TS%": 0.5, "experience": 0, "height": 2.042184832967569, "2P%": 0.3333333333333333, "MP": 14.483333333333333, "DRtg": 93.0, "ORtg": 100.0, "TRB%": 3.7, "FT/FGA": 0.0, "ORB": 0.0, "3P%": 1.0, "HOB": 0.10526315789473684}, "Trevor Ariza": {"STL%": 2.2, "": "us", "FT": 1.0, "weight": "215", "3P": 4.0, "TOV": 2.0, "STL/TOV": 0.5, "TSA": 9.32, "2PA": 4.0, "college": "University of California, Los Angeles", "FG": 5.0, "3PA": 4.0, "DRB": 8.0, "ORB%": 0.0, "BLK%": 0.0, "AST/TOV": 0.5, "position": "SF", "AST": 1.0, "FT%": 0.3333333333333333, "3PAr": 0.5, "PF": 2.0, "PTS": 15.0, "FGA": 8.0, "DRBr": 1.0, "ORBr": 0.0, "2P": 1.0, "STL": 1.0, "TRB": 8.0, "TOV%": 17.7, "AST%": 6.4, "FTAr": 0.375, "FTA": 3.0, "FIC": 12.875, "eFG%": 0.875, "BLK": 0.0, "birth_date": "1985-06-30", "FG%": 0.625, "2PAr": 0.5, "FTr": 0.375, "+/-": 26.0, "name": "Trevor Ariza", "USG%": 20.8, "DRB%": 31.5, "TS%": 0.8047210300429184, "experience": 6, "height": 2.0726652036088757, "2P%": 0.25, "MP": 25.933333333333334, "DRtg": 85.0, "ORtg": 128.0, "TRB%": 16.6, "FT/FGA": 0.125, "ORB": 0.0, "3P%": 1.0, "HOB": 0.15789473684210525}, "Chris Paul": {"STL%": 3.7, "": "us", "FT": 2.0, "weight": "175", "3P": 1.0, "TOV": 0.0, "STL/TOV": null, "TSA": 12.76, "2PA": 10.0, "college": "Wake Forest University", "FG": 4.0, "3PA": 1.0, "DRB": 5.0, "ORB%": 3.7, "BLK%": 0.0, "AST/TOV": null, "position": "PG", "AST": 6.0, "FT%": 0.5, "3PAr": 0.09090909090909091, "PF": 1.0, "PTS": 11.0, "FGA": 11.0, "DRBr": 0.8333333333333334, "ORBr": 0.16666666666666666, "2P": 3.0, "STL": 2.0, "TRB": 6.0, "TOV%": 0.0, "AST%": 29.7, "FTAr": 0.36363636363636365, "FTA": 4.0, "FIC": 13.5, "eFG%": 0.4090909090909091, "BLK": 0.0, "birth_date": "1985-05-06", "FG%": 0.36363636363636365, "2PAr": 0.9090909090909091, "FTr": 0.364, "+/-": 20.0, "name": "Chris Paul", "USG%": 19.9, "DRB%": 16.7, "TS%": 0.4310344827586207, "experience": 5, "height": 1.8288222384784198, "2P%": 0.3, "MP": 30.6, "DRtg": 85.0, "ORtg": 124.0, "TRB%": 10.6, "FT/FGA": 0.18181818181818182, "ORB": 1.0, "3P%": 1.0, "HOB": 0.2631578947368421}, "Marcus Thornton": {"STL%": 0.0, "": "us", "FT": 0.0, "weight": "205", "3P": 4.0, "TOV": 1.0, "STL/TOV": 0.0, "TSA": 10.0, "2PA": 6.0, "college": "Louisiana State University", "FG": 7.0, "3PA": 4.0, "DRB": 5.0, "ORB%": 0.0, "BLK%": 3.8, "AST/TOV": 2.0, "position": "SG", "AST": 2.0, "FT%": null, "3PAr": 0.4, "PF": 1.0, "PTS": 18.0, "FGA": 10.0, "DRBr": 1.0, "ORBr": 0.0, "2P": 3.0, "STL": 0.0, "TRB": 5.0, "TOV%": 9.1, "AST%": 17.4, "FTAr": 0.0, "FTA": 0.0, "FIC": 15.75, "eFG%": 0.9, "BLK": 1.0, "birth_date": "1987-06-05", "FG%": 0.7, "2PAr": 0.6, "FTr": 0.0, "+/-": -1.0, "name": "Marcus Thornton", "USG%": 22.4, "DRB%": 21.8, "TS%": 0.9, "experience": 1, "height": 1.9507437210436478, "2P%": 0.5, "MP": 23.383333333333333, "DRtg": 88.0, "ORtg": 164.0, "TRB%": 11.5, "FT/FGA": 0.0, "ORB": 0.0, "3P%": 1.0, "HOB": 0.23684210526315788}, "Didier Ilunga-Mbenga": {"STL%": 0.0, "": "cd", "FT": 0.0, "weight": "245", "3P": 0.0, "TOV": 1.0, "STL/TOV": 0.0, "TSA": 1.0, "2PA": 1.0, "college": "", "FG": 1.0, "3PA": 0.0, "DRB": 2.0, "ORB%": 26.7, "BLK%": 6.9, "AST/TOV": 0.0, "position": "C", "AST": 0.0, "FT%": null, "3PAr": 0.0, "PF": 2.0, "PTS": 2.0, "FGA": 1.0, "DRBr": 0.4, "ORBr": 0.6, "2P": 1.0, "STL": 0.0, "TRB": 5.0, "TOV%": 50.0, "AST%": 0.0, "FTAr": 0.0, "FTA": 0.0, "FIC": 4.75, "eFG%": 1.0, "BLK": 1.0, "birth_date": "1980-12-30", "FG%": 1.0, "2PAr": 1.0, "FTr": 0.0, "+/-": -4.0, "name": "Didier Ilunga-Mbenga", "USG%": 7.4, "DRB%": 15.9, "TS%": 1.0, "experience": 6, "height": 2.13362594489149, "2P%": 1.0, "MP": 12.85, "DRtg": 85.0, "ORtg": 124.0, "TRB%": 21.0, "FT/FGA": 0.0, "ORB": 3.0, "3P%": null, "HOB": 0.02631578947368421}, "Emeka Okafor": {"STL%": 0.0, "": "us", "FT": 1.0, "weight": "252", "3P": 0.0, "TOV": 1.0, "STL/TOV": 0.0, "TSA": 9.88, "2PA": 9.0, "college": "University of Connecticut", "FG": 4.0, "3PA": 0.0, "DRB": 9.0, "ORB%": 11.4, "BLK%": 14.7, "AST/TOV": 0.0, "position": "C", "AST": 0.0, "FT%": 0.5, "3PAr": 0.0, "PF": 3.0, "PTS": 9.0, "FGA": 9.0, "DRBr": 0.75, "ORBr": 0.25, "2P": 4.0, "STL": 0.0, "TRB": 12.0, "TOV%": 9.2, "AST%": 0.0, "FTAr": 0.2222222222222222, "FTA": 2.0, "FIC": 13.75, "eFG%": 0.4444444444444444, "BLK": 5.0, "birth_date": "1982-09-28", "FG%": 0.4444444444444444, "2PAr": 1.0, "FTr": 0.222, "+/-": 21.0, "name": "Emeka Okafor", "USG%": 17.2, "DRB%": 30.4, "TS%": 0.4554655870445344, "experience": 6, "height": 1.8593026091197267, "2P%": 0.4444444444444444, "MP": 30.2, "DRtg": 75.0, "ORtg": 102.0, "TRB%": 21.4, "FT/FGA": 0.1111111111111111, "ORB": 3.0, "3P%": null, "HOB": 0.10526315789473684}, "David Andersen": {"STL%": 0.0, "": "au", "FT": 0.0, "weight": "245", "3P": 0.0, "TOV": 0.0, "STL/TOV": null, "TSA": 1.0, "2PA": 1.0, "college": "", "FG": 0.0, "3PA": 0.0, "DRB": 3.0, "ORB%": 0.0, "BLK%": 0.0, "AST/TOV": null, "position": "PF", "AST": 0.0, "FT%": null, "3PAr": 0.0, "PF": 0.0, "PTS": 0.0, "FGA": 1.0, "DRBr": 1.0, "ORBr": 0.0, "2P": 0.0, "STL": 0.0, "TRB": 3.0, "TOV%": 0.0, "AST%": 0.0, "FTAr": 0.0, "FTA": 0.0, "FIC": 1.5, "eFG%": 0.0, "BLK": 0.0, "birth_date": "1980-06-23", "FG%": 0.0, "2PAr": 1.0, "FTr": 0.0, "+/-": 0.0, "name": "David Andersen", "USG%": 11.2, "DRB%": 71.8, "TS%": 0.0, "experience": 1, "height": 1.8623506461838577, "2P%": 0.0, "MP": 4.266666666666667, "DRtg": 81.0, "ORtg": 0.0, "TRB%": 37.9, "FT/FGA": 0.0, "ORB": 0.0, "3P%": null, "HOB": 0.0}, "Jarrett Jack": {"STL%": 2.7, "": "us", "FT": 1.0, "weight": "200", "3P": 0.0, "TOV": 1.0, "STL/TOV": 1.0, "TSA": 8.88, "2PA": 8.0, "college": "Georgia Institute of Technology", "FG": 4.0, "3PA": 0.0, "DRB": 1.0, "ORB%": 0.0, "BLK%": 0.0, "AST/TOV": 1.0, "position": "SG", "AST": 1.0, "FT%": 0.5, "3PAr": 0.0, "PF": 0.0, "PTS": 9.0, "FGA": 8.0, "DRBr": 1.0, "ORBr": 0.0, "2P": 4.0, "STL": 1.0, "TRB": 1.0, "TOV%": 10.1, "AST%": 8.1, "FTAr": 0.25, "FTA": 2.0, "FIC": 4.0, "eFG%": 0.5, "BLK": 0.0, "birth_date": "1983-10-28", "FG%": 0.5, "2PAr": 1.0, "FTr": 0.25, "+/-": -6.0, "name": "Jarrett Jack", "USG%": 22.7, "DRB%": 4.9, "TS%": 0.5067567567567567, "experience": 5, "height": 1.9202633504023408, "2P%": 0.5, "MP": 20.733333333333334, "DRtg": 89.0, "ORtg": 102.0, "TRB%": 2.6, "FT/FGA": 0.125, "ORB": 0.0, "3P%": null, "HOB": 0.13157894736842105}, "Jason Smith": {"STL%": 6.9, "": "us", "FT": 0.0, "weight": "245", "3P": 0.0, "TOV": 1.0, "STL/TOV": 2.0, "TSA": 3.0, "2PA": 3.0, "college": "Colorado State University", "FG": 0.0, "3PA": 0.0, "DRB": 2.0, "ORB%": 13.9, "BLK%": 0.0, "AST/TOV": 0.0, "position": "C", "AST": 0.0, "FT%": null, "3PAr": 0.0, "PF": 4.0, "PTS": 0.0, "FGA": 3.0, "DRBr": 0.5, "ORBr": 0.5, "2P": 0.0, "STL": 2.0, "TRB": 4.0, "TOV%": 25.0, "AST%": 0.0, "FTAr": 0.0, "FTA": 0.0, "FIC": 0.25, "eFG%": 0.0, "BLK": 0.0, "birth_date": "1986-03-02", "FG%": 0.0, "2PAr": 1.0, "FTr": 0.0, "+/-": 6.0, "name": "Jason Smith", "USG%": 11.6, "DRB%": 12.4, "TS%": 0.0, "experience": 2, "height": 2.13362594489149, "2P%": 0.0, "MP": 16.466666666666665, "DRtg": 78.0, "ORtg": 33.0, "TRB%": 13.1, "FT/FGA": 0.0, "ORB": 2.0, "3P%": null, "HOB": 0.0}}, "scores": {"1": "13", "3": "31", "2": "28", "4": "24", "T": "96"}, "name": "New Orleans Hornets", "totals": {"STL%": 9.5, "FT": 8.0, "2PA": 66.0, "FG": 38.0, "DRB": 42.0, "ORB%": 35.7, "AST": 19.0, "3PAr": 0.18518518518518517, "PF": 22.0, "FGA": 81.0, "DRBr": 0.7368421052631579, "2P": 26.0, "ORBr": 0.2631578947368421, "TOV%": 12.9, "AST%": 50.0, "FTAr": 0.18518518518518517, "FIC": 87.125, "eFG%": 0.5432098765432098, "FG%": 0.4691358024691358, "2PAr": 0.8148148148148148, "+/-": 24.0, "USG%": 100.0, "DRtg": 85.4, "2P%": 0.3939393939393939, "DRB%": 89.4, "ORtg": 113.9, "TRB%": 64.0, "ORB": 15.0, "3P": 12.0, "TOV": 13.0, "STL/TOV": 0.6153846153846154, "TSA": 87.6, "AST/TOV": 1.4615384615384615, "3PA": 15.0, "BLK%": 14.8, "FT%": 0.5333333333333333, "PTS": 96.0, "HOB": 1.5, "STL": 8.0, "TRB": 57.0, "FTA": 15.0, "BLK": 8.0, "FTr": 0.185, "TS%": 0.5479452054794521, "FT/FGA": 0.09876543209876543, "3P%": 0.8}}, "type": "Season"}