{"league": "nba", "code": "201211110BRK", "season": "2012-2013", "away": {"players": {"E'Twaun Moore": {"STL%": 0.0, "": "us", "FT": 1.0, "weight": "191", "3P": 1.0, "TOV": 4.0, "STL/TOV": 0.0, "TSA": 11.88, "2PA": 6.0, "college": "Purdue University", "FG": 3.0, "3PA": 5.0, "DRB": 1.0, "ORB%": 2.2, "BLK%": 0.0, "AST/TOV": 0.25, "position": "SG", "AST": 1.0, "FT%": 0.5, "3PAr": 0.45454545454545453, "PF": 4.0, "PTS": 8.0, "FGA": 11.0, "DRBr": 0.5, "ORBr": 0.5, "2P": 2.0, "STL": 0.0, "TRB": 2.0, "TOV%": 25.2, "AST%": 4.5, "FTAr": 0.18181818181818182, "FTA": 2.0, "FIC": -4.25, "eFG%": 0.3181818181818182, "BLK": 0.0, "birth_date": "1989-02-28", "FG%": 0.2727272727272727, "2PAr": 0.5454545454545454, "FTr": 0.182, "+/-": -8.0, "name": "E'Twaun Moore", "USG%": 18.2, "DRB%": 2.7, "TS%": 0.33670033670033667, "experience": 1, "height": 1.9507437210436478, "2P%": 0.3333333333333333, "MP": 40.65, "DRtg": 101.0, "ORtg": 54.0, "TRB%": 2.4, "FT/FGA": 0.09090909090909091, "ORB": 1.0, "3P%": 0.2, "HOB": 0.13333333333333333}, "Ish Smith": {"STL%": 7.4, "": "us", "FT": 0.0, "weight": "175", "3P": 0.0, "TOV": 1.0, "STL/TOV": 1.0, "TSA": 2.0, "2PA": 1.0, "college": "Wake Forest University", "FG": 0.0, "3PA": 1.0, "DRB": 1.0, "ORB%": 0.0, "BLK%": 0.0, "AST/TOV": 1.0, "position": "PG", "AST": 1.0, "FT%": null, "3PAr": 0.5, "PF": 1.0, "PTS": 0.0, "FGA": 2.0, "DRBr": 1.0, "ORBr": 0.0, "2P": 0.0, "STL": 1.0, "TRB": 1.0, "TOV%": 33.3, "AST%": 22.2, "FTAr": 0.0, "FTA": 0.0, "FIC": -0.25, "eFG%": 0.0, "BLK": 0.0, "birth_date": "1988-07-05", "FG%": 0.0, "2PAr": 0.5, "FTr": 0.0, "+/-": 0.0, "name": "Ish Smith", "USG%": 19.4, "DRB%": 15.5, "TS%": 0.0, "experience": 2, "height": 1.8288222384784198, "2P%": 0.0, "MP": 7.216666666666667, "DRtg": 79.0, "ORtg": 13.0, "TRB%": 6.9, "FT/FGA": 0.0, "ORB": 0.0, "3P%": 0.0, "HOB": 0.03333333333333333}, "J.J. Redick": {"STL%": 1.4, "": "us", "FT": 4.0, "weight": "190", "3P": 0.0, "TOV": 1.0, "STL/TOV": 1.0, "TSA": 14.2, "2PA": 8.0, "college": "Duke University", "FG": 3.0, "3PA": 4.0, "DRB": 2.0, "ORB%": 0.0, "BLK%": 0.0, "AST/TOV": 9.0, "position": "SG", "AST": 9.0, "FT%": 0.8, "3PAr": 0.3333333333333333, "PF": 3.0, "PTS": 10.0, "FGA": 12.0, "DRBr": 1.0, "ORBr": 0.0, "2P": 3.0, "STL": 1.0, "TRB": 2.0, "TOV%": 6.6, "AST%": 43.4, "FTAr": 0.4166666666666667, "FTA": 5.0, "FIC": 8.125, "eFG%": 0.25, "BLK": 0.0, "birth_date": "1984-06-24", "FG%": 0.25, "2PAr": 0.6666666666666666, "FTr": 0.417, "+/-": 3.0, "name": "J.J. Redick", "USG%": 18.7, "DRB%": 5.9, "TS%": 0.35211267605633806, "experience": 6, "height": 1.9507437210436478, "2P%": 0.375, "MP": 37.95, "DRtg": 97.0, "ORtg": 86.0, "TRB%": 2.6, "FT/FGA": 0.3333333333333333, "ORB": 0.0, "3P%": 0.0, "HOB": 0.4}, "Josh McRoberts": {"STL%": 0.0, "": "us", "FT": 0.0, "weight": "240", "3P": 0.0, "TOV": 0.0, "STL/TOV": null, "TSA": 1.0, "2PA": 1.0, "college": "Duke University", "FG": 1.0, "3PA": 0.0, "DRB": 1.0, "ORB%": 0.0, "BLK%": 0.0, "AST/TOV": null, "position": "PF", "AST": 2.0, "FT%": null, "3PAr": 0.0, "PF": 0.0, "PTS": 2.0, "FGA": 1.0, "DRBr": 1.0, "ORBr": 0.0, "2P": 1.0, "STL": 0.0, "TRB": 1.0, "TOV%": 0.0, "AST%": 27.2, "FTAr": 0.0, "FTA": 0.0, "FIC": 4.0, "eFG%": 1.0, "BLK": 0.0, "birth_date": "1987-02-28", "FG%": 1.0, "2PAr": 1.0, "FTr": 0.0, "+/-": -25.0, "name": "Josh McRoberts", "USG%": 3.5, "DRB%": 8.4, "TS%": 1.0, "experience": 5, "height": 1.8593026091197267, "2P%": 1.0, "MP": 13.35, "DRtg": 99.0, "ORtg": 201.0, "TRB%": 3.7, "FT/FGA": 0.0, "ORB": 0.0, "3P%": null, "HOB": 0.1}, "Arron Afflalo": {"STL%": 1.3, "": "us", "FT": 5.0, "weight": "210", "3P": 0.0, "TOV": 1.0, "STL/TOV": 1.0, "TSA": 19.2, "2PA": 14.0, "college": "University of California, Los Angeles", "FG": 7.0, "3PA": 3.0, "DRB": 7.0, "ORB%": 0.0, "BLK%": 2.2, "AST/TOV": 5.0, "position": "SF", "AST": 5.0, "FT%": 1.0, "3PAr": 0.17647058823529413, "PF": 1.0, "PTS": 19.0, "FGA": 17.0, "DRBr": 1.0, "ORBr": 0.0, "2P": 7.0, "STL": 1.0, "TRB": 7.0, "TOV%": 5.0, "AST%": 27.0, "FTAr": 0.29411764705882354, "FTA": 5.0, "FIC": 15.125, "eFG%": 0.4117647058823529, "BLK": 1.0, "birth_date": "1985-10-15", "FG%": 0.4117647058823529, "2PAr": 0.8235294117647058, "FTr": 0.294, "+/-": 4.0, "name": "Arron Afflalo", "USG%": 23.1, "DRB%": 19.2, "TS%": 0.4947916666666667, "experience": 5, "height": 1.9812240916849548, "2P%": 0.5, "MP": 40.8, "DRtg": 91.0, "ORtg": 102.0, "TRB%": 8.5, "FT/FGA": 0.29411764705882354, "ORB": 0.0, "3P%": 0.0, "HOB": 0.4}, "Andrew Nicholson": {"STL%": 0.0, "": "ca", "FT": 0.0, "weight": "250", "3P": 0.0, "TOV": 0.0, "STL/TOV": null, "TSA": 1.0, "2PA": 1.0, "college": "St. Bonaventure University", "FG": 0.0, "3PA": 0.0, "DRB": 0.0, "ORB%": 0.0, "BLK%": 0.0, "AST/TOV": null, "position": "PF", "AST": 0.0, "FT%": null, "3PAr": 0.0, "PF": 1.0, "PTS": 0.0, "FGA": 1.0, "DRBr": null, "ORBr": null, "2P": 0.0, "STL": 0.0, "TRB": 0.0, "TOV%": 0.0, "AST%": 0.0, "FTAr": 0.0, "FTA": 0.0, "FIC": -1.25, "eFG%": 0.0, "BLK": 0.0, "birth_date": "1989-12-08", "FG%": 0.0, "2PAr": 1.0, "FTr": 0.0, "+/-": 1.0, "name": "Andrew Nicholson", "USG%": 14.4, "DRB%": 0.0, "TS%": 0.0, "experience": 0, "height": 2.103145574250183, "2P%": 0.0, "MP": 3.2333333333333334, "DRtg": 101.0, "ORtg": 0.0, "TRB%": 0.0, "FT/FGA": 0.0, "ORB": 0.0, "3P%": null, "HOB": 0.0}, "Maurice Harkless": {"STL%": 0.0, "": "us", "FT": 0.0, "weight": "215", "3P": 0.0, "TOV": 1.0, "STL/TOV": 0.0, "TSA": 2.0, "2PA": 2.0, "college": "St. John's University", "FG": 0.0, "3PA": 0.0, "DRB": 1.0, "ORB%": 16.2, "BLK%": 0.0, "AST/TOV": 0.0, "position": "SF", "AST": 0.0, "FT%": null, "3PAr": 0.0, "PF": 3.0, "PTS": 0.0, "FGA": 2.0, "DRBr": 0.3333333333333333, "ORBr": 0.6666666666666666, "2P": 0.0, "STL": 0.0, "TRB": 3.0, "TOV%": 33.3, "AST%": 0.0, "FTAr": 0.0, "FTA": 0.0, "FIC": -1.25, "eFG%": 0.0, "BLK": 0.0, "birth_date": "1993-05-11", "FG%": 0.0, "2PAr": 1.0, "FTr": 0.0, "+/-": -14.0, "name": "Maurice Harkless", "USG%": 12.8, "DRB%": 10.2, "TS%": 0.0, "experience": 0, "height": 2.103145574250183, "2P%": 0.0, "MP": 10.95, "DRtg": 97.0, "ORtg": 33.0, "TRB%": 13.6, "FT/FGA": 0.0, "ORB": 2.0, "3P%": null, "HOB": 0.0}, "Nikola Vucevic": {"STL%": 0.0, "": "ch", "FT": 2.0, "weight": "260", "3P": 0.0, "TOV": 1.0, "STL/TOV": 0.0, "TSA": 15.88, "2PA": 15.0, "college": "University of Southern California", "FG": 6.0, "3PA": 0.0, "DRB": 9.0, "ORB%": 8.9, "BLK%": 2.2, "AST/TOV": 3.0, "position": "C", "AST": 3.0, "FT%": 1.0, "3PAr": 0.0, "PF": 4.0, "PTS": 14.0, "FGA": 15.0, "DRBr": 0.6923076923076923, "ORBr": 0.3076923076923077, "2P": 6.0, "STL": 0.0, "TRB": 13.0, "TOV%": 5.9, "AST%": 15.9, "FTAr": 0.13333333333333333, "FTA": 2.0, "FIC": 13.75, "eFG%": 0.4, "BLK": 1.0, "birth_date": "1990-10-24", "FG%": 0.4, "2PAr": 1.0, "FTr": 0.133, "+/-": 1.0, "name": "Nikola Vucevic", "USG%": 19.8, "DRB%": 25.3, "TS%": 0.44080604534005036, "experience": 1, "height": 2.13362594489149, "2P%": 0.4, "MP": 39.75, "DRtg": 91.0, "ORtg": 96.0, "TRB%": 16.2, "FT/FGA": 0.13333333333333333, "ORB": 4.0, "3P%": null, "HOB": 0.3}, "Glen Davis": {"STL%": 4.2, "": "us", "FT": 1.0, "weight": "289", "3P": 0.0, "TOV": 2.0, "STL/TOV": 1.5, "TSA": 21.88, "2PA": 21.0, "college": "Louisiana State University", "FG": 9.0, "3PA": 0.0, "DRB": 8.0, "ORB%": 4.7, "BLK%": 4.7, "AST/TOV": 0.5, "position": "PF", "AST": 1.0, "FT%": 0.5, "3PAr": 0.0, "PF": 4.0, "PTS": 19.0, "FGA": 21.0, "DRBr": 0.8, "ORBr": 0.2, "2P": 9.0, "STL": 3.0, "TRB": 10.0, "TOV%": 8.4, "AST%": 6.8, "FTAr": 0.09523809523809523, "FTA": 2.0, "FIC": 12.5, "eFG%": 0.42857142857142855, "BLK": 2.0, "birth_date": "1986-01-01", "FG%": 0.42857142857142855, "2PAr": 1.0, "FTr": 0.095, "+/-": -1.0, "name": "Glen Davis", "USG%": 29.3, "DRB%": 23.5, "TS%": 0.4341864716636198, "experience": 5, "height": 2.103145574250183, "2P%": 0.42857142857142855, "MP": 38.05, "DRtg": 81.0, "ORtg": 81.0, "TRB%": 13.0, "FT/FGA": 0.047619047619047616, "ORB": 2.0, "3P%": null, "HOB": 0.3333333333333333}, "Gustavo Ayon": {"STL%": 0.0, "": "mx", "FT": 0.0, "weight": "250", "3P": 0.0, "TOV": 0.0, "STL/TOV": null, "TSA": 2.88, "2PA": 2.0, "college": "", "FG": 1.0, "3PA": 0.0, "DRB": 1.0, "ORB%": 22.1, "BLK%": 0.0, "AST/TOV": null, "position": "C", "AST": 0.0, "FT%": 0.0, "3PAr": 0.0, "PF": 1.0, "PTS": 2.0, "FGA": 2.0, "DRBr": 0.3333333333333333, "ORBr": 0.6666666666666666, "2P": 1.0, "STL": 0.0, "TRB": 3.0, "TOV%": 0.0, "AST%": 0.0, "FTAr": 1.0, "FTA": 2.0, "FIC": 2.0, "eFG%": 0.5, "BLK": 0.0, "birth_date": "1985-04-01", "FG%": 0.5, "2PAr": 1.0, "FTr": 1.0, "+/-": -1.0, "name": "Gustavo Ayon", "USG%": 16.7, "DRB%": 13.9, "TS%": 0.3472222222222222, "experience": 1, "height": 1.8593026091197267, "2P%": 0.5, "MP": 8.05, "DRtg": 96.0, "ORtg": 87.0, "TRB%": 18.4, "FT/FGA": 0.0, "ORB": 2.0, "3P%": null, "HOB": 0.03333333333333333}}, "scores": {"1": "17", "3": "18", "2": "18", "4": "21", "T": "74"}, "name": "Orlando Magic", "totals": {"STL%": 6.7, "FT": 13.0, "2PA": 71.0, "FG": 30.0, "DRB": 31.0, "ORB%": 20.4, "AST": 22.0, "3PAr": 0.15476190476190477, "PF": 22.0, "FGA": 84.0, "DRBr": 0.7380952380952381, "2P": 29.0, "ORBr": 0.2619047619047619, "TOV%": 10.7, "AST%": 73.3, "FTAr": 0.21428571428571427, "FIC": 48.5, "eFG%": 0.3630952380952381, "FG%": 0.35714285714285715, "2PAr": 0.8452380952380952, "+/-": -8.0, "USG%": 100.0, "DRtg": 91.7, "2P%": 0.4084507042253521, "DRB%": 72.1, "ORtg": 82.8, "TRB%": 43.3, "ORB": 11.0, "3P": 1.0, "TOV": 11.0, "STL/TOV": 0.5454545454545454, "TSA": 91.92, "AST/TOV": 2.0, "3PA": 13.0, "BLK%": 7.4, "FT%": 0.7222222222222222, "PTS": 74.0, "HOB": 1.7333333333333334, "STL": 6.0, "TRB": 42.0, "FTA": 18.0, "BLK": 4.0, "FTr": 0.214, "TS%": 0.40252393385552654, "FT/FGA": 0.15476190476190477, "3P%": 0.07692307692307693}}, "time": "15:00:00", "country": "United States", "date": "2012-11-11", "home": {"players": {"Keith Bogans": {"STL%": 0.0, "": "us", "FT": 0.0, "weight": "215", "3P": 0.0, "TOV": 0.0, "STL/TOV": null, "TSA": 5.0, "2PA": 1.0, "college": "University of Kentucky", "FG": 0.0, "3PA": 4.0, "DRB": 2.0, "ORB%": 6.1, "BLK%": 0.0, "AST/TOV": null, "position": "SG", "AST": 3.0, "FT%": null, "3PAr": 0.8, "PF": 0.0, "PTS": 0.0, "FGA": 5.0, "DRBr": 0.6666666666666666, "ORBr": 0.3333333333333333, "2P": 0.0, "STL": 0.0, "TRB": 3.0, "TOV%": 0.0, "AST%": 27.0, "FTAr": 0.0, "FTA": 0.0, "FIC": 1.75, "eFG%": 0.0, "BLK": 0.0, "birth_date": "1980-05-12", "FG%": 0.0, "2PAr": 0.2, "FTr": 0.0, "+/-": 10.0, "name": "Keith Bogans", "USG%": 12.5, "DRB%": 9.7, "TS%": 0.0, "experience": 9, "height": 1.9812240916849548, "2P%": 0.0, "MP": 18.416666666666668, "DRtg": 89.0, "ORtg": 43.0, "TRB%": 8.1, "FT/FGA": 0.0, "ORB": 1.0, "3P%": 0.0, "HOB": 0.10344827586206896}, "Kris Humphries": {"STL%": 0.0, "": "us", "FT": 2.0, "weight": "235", "3P": 0.0, "TOV": 1.0, "STL/TOV": 0.0, "TSA": 11.88, "2PA": 11.0, "college": "University of Minnesota", "FG": 6.0, "3PA": 0.0, "DRB": 15.0, "ORB%": 19.7, "BLK%": 2.0, "AST/TOV": 0.0, "position": "PF", "AST": 0.0, "FT%": 1.0, "3PAr": 0.0, "PF": 5.0, "PTS": 14.0, "FGA": 11.0, "DRBr": 0.7142857142857143, "ORBr": 0.2857142857142857, "2P": 6.0, "STL": 0.0, "TRB": 21.0, "TOV%": 7.8, "AST%": 0.0, "FTAr": 0.18181818181818182, "FTA": 2.0, "FIC": 19.75, "eFG%": 0.5454545454545454, "BLK": 1.0, "birth_date": "1985-02-06", "FG%": 0.5454545454545454, "2PAr": 1.0, "FTr": 0.182, "+/-": -1.0, "name": "Kris Humphries", "USG%": 17.5, "DRB%": 39.2, "TS%": 0.5892255892255892, "experience": 8, "height": 2.103145574250183, "2P%": 0.5454545454545454, "MP": 34.016666666666666, "DRtg": 76.0, "ORtg": 123.0, "TRB%": 30.5, "FT/FGA": 0.18181818181818182, "ORB": 6.0, "3P%": null, "HOB": 0.20689655172413793}, "Tyshawn Taylor": {"STL%": 0.0, "": "us", "FT": 0.0, "weight": "185", "3P": 0.0, "TOV": 0.0, "STL/TOV": null, "TSA": 0.0, "2PA": 0.0, "college": "University of Kansas", "FG": 0.0, "3PA": 0.0, "DRB": 0.0, "ORB%": 0.0, "BLK%": 0.0, "AST/TOV": null, "position": "PG", "AST": 0.0, "FT%": null, "3PAr": null, "PF": 0.0, "PTS": 0.0, "FGA": 0.0, "DRBr": null, "ORBr": null, "2P": 0.0, "STL": 0.0, "TRB": 0.0, "TOV%": null, "AST%": 0.0, "FTAr": null, "FTA": 0.0, "FIC": 0.0, "eFG%": null, "BLK": 0.0, "birth_date": "1990-04-12", "FG%": null, "2PAr": null, "FTr": null, "+/-": 0.0, "name": "Tyshawn Taylor", "USG%": 0.0, "DRB%": 0.0, "TS%": null, "experience": 0, "height": 1.9202633504023408, "2P%": null, "MP": 0.11666666666666667, "DRtg": 93.0, "ORtg": 0.0, "TRB%": 0.0, "FT/FGA": null, "ORB": 0.0, "3P%": null, "HOB": 0.0}, "Deron Williams": {"STL%": 0.0, "": "us", "FT": 4.0, "weight": "200", "3P": 3.0, "TOV": 3.0, "STL/TOV": 0.0, "TSA": 14.64, "2PA": 5.0, "college": "University of Illinois at Urbana-Champaign", "FG": 5.0, "3PA": 7.0, "DRB": 7.0, "ORB%": 0.0, "BLK%": 3.7, "AST/TOV": 2.3333333333333335, "position": "PG", "AST": 7.0, "FT%": 0.6666666666666666, "3PAr": 0.5833333333333334, "PF": 2.0, "PTS": 17.0, "FGA": 12.0, "DRBr": 1.0, "ORBr": 0.0, "2P": 2.0, "STL": 0.0, "TRB": 7.0, "TOV%": 17.0, "AST%": 41.4, "FTAr": 0.5, "FTA": 6.0, "FIC": 16.0, "eFG%": 0.5416666666666666, "BLK": 2.0, "birth_date": "1984-06-26", "FG%": 0.4166666666666667, "2PAr": 0.4166666666666667, "FTr": 0.5, "+/-": 0.0, "name": "Deron Williams", "USG%": 22.5, "DRB%": 17.2, "TS%": 0.5806010928961748, "experience": 7, "height": 1.9202633504023408, "2P%": 0.4, "MP": 36.233333333333334, "DRtg": 83.0, "ORtg": 110.0, "TRB%": 9.6, "FT/FGA": 0.3333333333333333, "ORB": 0.0, "3P%": 0.42857142857142855, "HOB": 0.41379310344827586}, "Jerry Stackhouse": {"STL%": 0.0, "": "us", "FT": 0.0, "weight": "218", "3P": 1.0, "TOV": 0.0, "STL/TOV": null, "TSA": 3.0, "2PA": 2.0, "college": "University of North Carolina", "FG": 2.0, "3PA": 1.0, "DRB": 0.0, "ORB%": 0.0, "BLK%": 4.6, "AST/TOV": null, "position": "SF", "AST": 2.0, "FT%": null, "3PAr": 0.3333333333333333, "PF": 2.0, "PTS": 5.0, "FGA": 3.0, "DRBr": null, "ORBr": null, "2P": 1.0, "STL": 0.0, "TRB": 0.0, "TOV%": 0.0, "AST%": 28.9, "FTAr": 0.0, "FTA": 0.0, "FIC": 4.75, "eFG%": 0.8333333333333334, "BLK": 1.0, "birth_date": "1974-11-05", "FG%": 0.6666666666666666, "2PAr": 0.6666666666666666, "FTr": 0.0, "+/-": 12.0, "name": "Jerry Stackhouse", "USG%": 9.4, "DRB%": 0.0, "TS%": 0.8333333333333334, "experience": 17, "height": 2.0117044623262617, "2P%": 0.5, "MP": 14.783333333333333, "DRtg": 89.0, "ORtg": 174.0, "TRB%": 0.0, "FT/FGA": 0.0, "ORB": 0.0, "3P%": 1.0, "HOB": 0.13793103448275862}, "Josh Childress": {"STL%": 0.0, "": "us", "FT": 0.0, "weight": "210", "3P": 0.0, "TOV": 0.0, "STL/TOV": null, "TSA": 0.0, "2PA": 0.0, "college": "Stanford University", "FG": 0.0, "3PA": 0.0, "DRB": 3.0, "ORB%": 0.0, "BLK%": 0.0, "AST/TOV": null, "position": "SF", "AST": 0.0, "FT%": null, "3PAr": null, "PF": 0.0, "PTS": 0.0, "FGA": 0.0, "DRBr": 1.0, "ORBr": 0.0, "2P": 0.0, "STL": 0.0, "TRB": 3.0, "TOV%": null, "AST%": 0.0, "FTAr": null, "FTA": 0.0, "FIC": 2.25, "eFG%": null, "BLK": 0.0, "birth_date": "1983-06-20", "FG%": null, "2PAr": null, "FTr": null, "+/-": -9.0, "name": "Josh Childress", "USG%": 0.0, "DRB%": 27.1, "TS%": null, "experience": 6, "height": 2.0726652036088757, "2P%": null, "MP": 9.85, "DRtg": 83.0, "ORtg": 0.0, "TRB%": 15.1, "FT/FGA": null, "ORB": 0.0, "3P%": null, "HOB": 0.0}, "C.J. Watson": {"STL%": 4.5, "": "us", "FT": 2.0, "weight": "175", "3P": 1.0, "TOV": 0.0, "STL/TOV": null, "TSA": 10.32, "2PA": 2.0, "college": "University of Tennessee", "FG": 2.0, "3PA": 7.0, "DRB": 1.0, "ORB%": 0.0, "BLK%": 0.0, "AST/TOV": null, "position": "PG", "AST": 1.0, "FT%": 0.6666666666666666, "3PAr": 0.7777777777777778, "PF": 2.0, "PTS": 7.0, "FGA": 9.0, "DRBr": 1.0, "ORBr": 0.0, "2P": 1.0, "STL": 2.0, "TRB": 1.0, "TOV%": 0.0, "AST%": 8.1, "FTAr": 0.3333333333333333, "FTA": 3.0, "FIC": 1.875, "eFG%": 0.2777777777777778, "BLK": 0.0, "birth_date": "1984-04-17", "FG%": 0.2222222222222222, "2PAr": 0.2222222222222222, "FTr": 0.333, "+/-": -1.0, "name": "C.J. Watson", "USG%": 20.0, "DRB%": 3.7, "TS%": 0.3391472868217054, "experience": 5, "height": 1.889782979761034, "2P%": 0.5, "MP": 23.816666666666666, "DRtg": 82.0, "ORtg": 82.0, "TRB%": 2.1, "FT/FGA": 0.2222222222222222, "ORB": 0.0, "3P%": 0.14285714285714285, "HOB": 0.10344827586206896}, "Andray Blatche": {"STL%": 0.0, "": "us", "FT": 0.0, "weight": "235", "3P": 0.0, "TOV": 2.0, "STL/TOV": 0.0, "TSA": 6.0, "2PA": 6.0, "college": "", "FG": 1.0, "3PA": 0.0, "DRB": 6.0, "ORB%": 9.1, "BLK%": 5.5, "AST/TOV": 0.0, "position": "C", "AST": 0.0, "FT%": null, "3PAr": 0.0, "PF": 2.0, "PTS": 2.0, "FGA": 6.0, "DRBr": 0.8571428571428571, "ORBr": 0.14285714285714285, "2P": 1.0, "STL": 0.0, "TRB": 7.0, "TOV%": 25.0, "AST%": 0.0, "FTAr": 0.0, "FTA": 0.0, "FIC": 1.0, "eFG%": 0.16666666666666666, "BLK": 1.0, "birth_date": "1986-08-22", "FG%": 0.16666666666666666, "2PAr": 1.0, "FTr": 0.0, "+/-": 4.0, "name": "Andray Blatche", "USG%": 30.2, "DRB%": 43.7, "TS%": 0.16666666666666666, "experience": 7, "height": 1.8623506461838577, "2P%": 0.16666666666666666, "MP": 12.216666666666667, "DRtg": 71.0, "ORtg": 34.0, "TRB%": 28.4, "FT/FGA": 0.0, "ORB": 1.0, "3P%": null, "HOB": 0.034482758620689655}, "Brook Lopez": {"STL%": 0.0, "": "us", "FT": 2.0, "weight": "275", "3P": 0.0, "TOV": 7.0, "STL/TOV": 0.0, "TSA": 18.88, "2PA": 18.0, "college": "Stanford University", "FG": 9.0, "3PA": 0.0, "DRB": 2.0, "ORB%": 3.2, "BLK%": 5.8, "AST/TOV": 0.42857142857142855, "position": "C", "AST": 3.0, "FT%": 1.0, "3PAr": 0.0, "PF": 3.0, "PTS": 20.0, "FGA": 18.0, "DRBr": 0.6666666666666666, "ORBr": 0.3333333333333333, "2P": 9.0, "STL": 0.0, "TRB": 3.0, "TOV%": 27.0, "AST%": 24.8, "FTAr": 0.1111111111111111, "FTA": 2.0, "FIC": 5.75, "eFG%": 0.5, "BLK": 3.0, "birth_date": "1988-04-01", "FG%": 0.5, "2PAr": 1.0, "FTr": 0.111, "+/-": 4.0, "name": "Brook Lopez", "USG%": 34.2, "DRB%": 5.1, "TS%": 0.5296610169491526, "experience": 4, "height": 2.13362594489149, "2P%": 0.5, "MP": 34.916666666666664, "DRtg": 86.0, "ORtg": 80.0, "TRB%": 4.3, "FT/FGA": 0.1111111111111111, "ORB": 1.0, "3P%": null, "HOB": 0.41379310344827586}, "Reggie Evans": {"STL%": 7.5, "": "us", "FT": 2.0, "weight": "245", "3P": 0.0, "TOV": 1.0, "STL/TOV": 2.0, "TSA": 3.64, "2PA": 1.0, "college": "University of Iowa", "FG": 1.0, "3PA": 0.0, "DRB": 5.0, "ORB%": 15.7, "BLK%": 0.0, "AST/TOV": 0.0, "position": "PF", "AST": 0.0, "FT%": 0.3333333333333333, "3PAr": 0.0, "PF": 1.0, "PTS": 4.0, "FGA": 1.0, "DRBr": 0.7142857142857143, "ORBr": 0.2857142857142857, "2P": 1.0, "STL": 2.0, "TRB": 7.0, "TOV%": 21.6, "AST%": 0.0, "FTAr": 6.0, "FTA": 6.0, "FIC": 7.25, "eFG%": 1.0, "BLK": 0.0, "birth_date": "1980-05-18", "FG%": 1.0, "2PAr": 1.0, "FTr": 6.0, "+/-": 9.0, "name": "Reggie Evans", "USG%": 15.0, "DRB%": 31.2, "TS%": 0.5494505494505494, "experience": 10, "height": 2.0726652036088757, "2P%": 1.0, "MP": 14.25, "DRtg": 66.0, "ORtg": 92.0, "TRB%": 24.3, "FT/FGA": 2.0, "ORB": 2.0, "3P%": null, "HOB": 0.034482758620689655}, "Joe Johnson": {"STL%": 1.3, "": "us", "FT": 5.0, "weight": "240", "3P": 2.0, "TOV": 1.0, "STL/TOV": 1.0, "TSA": 15.64, "2PA": 8.0, "college": "University of Arkansas", "FG": 3.0, "3PA": 5.0, "DRB": 2.0, "ORB%": 2.7, "BLK%": 0.0, "AST/TOV": 4.0, "position": "SG", "AST": 4.0, "FT%": 0.8333333333333334, "3PAr": 0.38461538461538464, "PF": 0.0, "PTS": 13.0, "FGA": 13.0, "DRBr": 0.6666666666666666, "ORBr": 0.3333333333333333, "2P": 1.0, "STL": 1.0, "TRB": 3.0, "TOV%": 6.0, "AST%": 18.2, "FTAr": 0.46153846153846156, "FTA": 6.0, "FIC": 7.5, "eFG%": 0.3076923076923077, "BLK": 0.0, "birth_date": "1981-06-29", "FG%": 0.23076923076923078, "2PAr": 0.6153846153846154, "FTr": 0.462, "+/-": 12.0, "name": "Joe Johnson", "USG%": 18.6, "DRB%": 4.3, "TS%": 0.4156010230179028, "experience": 11, "height": 2.042184832967569, "2P%": 0.125, "MP": 41.38333333333333, "DRtg": 89.0, "ORtg": 99.0, "TRB%": 3.6, "FT/FGA": 0.38461538461538464, "ORB": 1.0, "3P%": 0.4, "HOB": 0.2413793103448276}}, "scores": {"1": "35", "3": "13", "2": "15", "4": "19", "T": "82"}, "name": "Brooklyn Nets", "totals": {"STL%": 5.6, "FT": 17.0, "2PA": 54.0, "FG": 29.0, "DRB": 43.0, "ORB%": 27.9, "AST": 20.0, "3PAr": 0.3076923076923077, "PF": 17.0, "FGA": 78.0, "DRBr": 0.7818181818181819, "2P": 22.0, "ORBr": 0.21818181818181817, "TOV%": 14.4, "AST%": 69.0, "FTAr": 0.32051282051282054, "FIC": 67.875, "eFG%": 0.4166666666666667, "FG%": 0.3717948717948718, "2PAr": 0.6923076923076923, "+/-": 8.0, "USG%": 100.0, "DRtg": 82.8, "2P%": 0.4074074074074074, "DRB%": 79.6, "ORtg": 91.7, "TRB%": 56.7, "ORB": 12.0, "3P": 7.0, "TOV": 15.0, "STL/TOV": 0.3333333333333333, "TSA": 89.0, "AST/TOV": 1.3333333333333333, "3PA": 24.0, "BLK%": 11.3, "FT%": 0.68, "PTS": 82.0, "HOB": 1.6896551724137931, "STL": 5.0, "TRB": 55.0, "FTA": 25.0, "BLK": 8.0, "FTr": 0.321, "TS%": 0.4606741573033708, "FT/FGA": 0.21794871794871795, "3P%": 0.2916666666666667}}, "type": "Season"}