{"league": "nba", "code": "201304050UTA", "season": "2012-2013", "away": {"players": {"Darius Miller": {"STL%": 0.0, "": "us", "FT": 0.0, "weight": "235", "3P": 0.0, "TOV": 0.0, "STL/TOV": null, "TSA": 2.0, "2PA": 0.0, "college": "University of Kentucky", "FG": 0.0, "3PA": 2.0, "DRB": 0.0, "ORB%": 0.0, "BLK%": 0.0, "AST/TOV": null, "position": "SF", "AST": 0.0, "FT%": null, "3PAr": 1.0, "PF": 5.0, "PTS": 0.0, "FGA": 2.0, "DRBr": null, "ORBr": null, "2P": 0.0, "STL": 0.0, "TRB": 0.0, "TOV%": 0.0, "AST%": 0.0, "FTAr": 0.0, "FTA": 0.0, "FIC": -4.0, "eFG%": 0.0, "BLK": 0.0, "birth_date": "1990-03-21", "FG%": 0.0, "2PAr": 0.0, "FTr": 0.0, "+/-": -9.0, "name": "Darius Miller", "USG%": 7.6, "DRB%": 0.0, "TS%": 0.0, "experience": 0, "height": 2.0726652036088757, "2P%": null, "MP": 12.433333333333334, "DRtg": 117.0, "ORtg": 0.0, "TRB%": 0.0, "FT/FGA": 0.0, "ORB": 0.0, "3P%": 0.0, "HOB": 0.0}, "Greivis Vasquez": {"STL%": 0.0, "": "ve", "FT": 2.0, "weight": "217", "3P": 1.0, "TOV": 5.0, "STL/TOV": 0.0, "TSA": 14.32, "2PA": 11.0, "college": "University of Maryland", "FG": 9.0, "3PA": 2.0, "DRB": 5.0, "ORB%": 0.0, "BLK%": 0.0, "AST/TOV": 1.8, "position": "PG", "AST": 9.0, "FT%": 0.6666666666666666, "3PAr": 0.15384615384615385, "PF": 3.0, "PTS": 21.0, "FGA": 13.0, "DRBr": 1.0, "ORBr": 0.0, "2P": 8.0, "STL": 0.0, "TRB": 5.0, "TOV%": 25.9, "AST%": 57.7, "FTAr": 0.23076923076923078, "FTA": 3.0, "FIC": 16.375, "eFG%": 0.7307692307692307, "BLK": 0.0, "birth_date": "1987-01-16", "FG%": 0.6923076923076923, "2PAr": 0.8461538461538461, "FTr": 0.231, "+/-": 7.0, "name": "Greivis Vasquez", "USG%": 24.7, "DRB%": 18.1, "TS%": 0.7332402234636871, "experience": 2, "height": 2.0117044623262617, "2P%": 0.7272727272727273, "MP": 36.916666666666664, "DRtg": 114.0, "ORtg": 120.0, "TRB%": 8.7, "FT/FGA": 0.15384615384615385, "ORB": 0.0, "3P%": 0.5, "HOB": 0.5625}, "Robin Lopez": {"STL%": 1.6, "": "us", "FT": 2.0, "weight": "255", "3P": 0.0, "TOV": 0.0, "STL/TOV": null, "TSA": 9.88, "2PA": 9.0, "college": "Stanford University", "FG": 5.0, "3PA": 0.0, "DRB": 5.0, "ORB%": 7.0, "BLK%": 2.7, "AST/TOV": null, "position": "C", "AST": 1.0, "FT%": 1.0, "3PAr": 0.0, "PF": 0.0, "PTS": 12.0, "FGA": 9.0, "DRBr": 0.7142857142857143, "ORBr": 0.2857142857142857, "2P": 5.0, "STL": 1.0, "TRB": 7.0, "TOV%": 0.0, "AST%": 5.4, "FTAr": 0.2222222222222222, "FTA": 2.0, "FIC": 13.25, "eFG%": 0.5555555555555556, "BLK": 1.0, "birth_date": "1988-04-01", "FG%": 0.5555555555555556, "2PAr": 1.0, "FTr": 0.222, "+/-": 3.0, "name": "Robin Lopez", "USG%": 13.2, "DRB%": 18.9, "TS%": 0.6072874493927125, "experience": 4, "height": 2.13362594489149, "2P%": 0.5555555555555556, "MP": 35.3, "DRtg": 109.0, "ORtg": 141.0, "TRB%": 12.7, "FT/FGA": 0.2222222222222222, "ORB": 2.0, "3P%": null, "HOB": 0.1875}, "Roger Mason": {"STL%": 13.3, "": "us", "FT": 0.0, "weight": "200", "3P": 0.0, "TOV": 0.0, "STL/TOV": null, "TSA": 1.0, "2PA": 1.0, "college": "University of Virginia", "FG": 0.0, "3PA": 0.0, "DRB": 0.0, "ORB%": 0.0, "BLK%": 0.0, "AST/TOV": null, "position": "SG", "AST": 0.0, "FT%": null, "3PAr": 0.0, "PF": 0.0, "PTS": 0.0, "FGA": 1.0, "DRBr": null, "ORBr": null, "2P": 0.0, "STL": 1.0, "TRB": 0.0, "TOV%": 0.0, "AST%": 0.0, "FTAr": 0.0, "FTA": 0.0, "FIC": 0.25, "eFG%": 0.0, "BLK": 0.0, "birth_date": "1980-09-10", "FG%": 0.0, "2PAr": 1.0, "FTr": 0.0, "+/-": -3.0, "name": "Roger Mason", "USG%": 11.3, "DRB%": 0.0, "TS%": 0.0, "experience": 8, "height": 1.9812240916849548, "2P%": 0.0, "MP": 4.183333333333334, "DRtg": 90.0, "ORtg": 0.0, "TRB%": 0.0, "FT/FGA": 0.0, "ORB": 0.0, "3P%": null, "HOB": 0.0}, "Eric Gordon": {"STL%": 0.0, "": "us", "FT": 2.0, "weight": "215", "3P": 1.0, "TOV": 3.0, "STL/TOV": 0.0, "TSA": 3.88, "2PA": 1.0, "college": "Indiana University", "FG": 2.0, "3PA": 2.0, "DRB": 1.0, "ORB%": 0.0, "BLK%": 0.0, "AST/TOV": 0.6666666666666666, "position": "SG", "AST": 2.0, "FT%": 1.0, "3PAr": 0.6666666666666666, "PF": 1.0, "PTS": 7.0, "FGA": 3.0, "DRBr": 1.0, "ORBr": 0.0, "2P": 1.0, "STL": 0.0, "TRB": 1.0, "TOV%": 43.6, "AST%": 20.4, "FTAr": 0.6666666666666666, "FTA": 2.0, "FIC": 3.25, "eFG%": 0.8333333333333334, "BLK": 0.0, "birth_date": "1988-12-25", "FG%": 0.6666666666666666, "2PAr": 0.3333333333333333, "FTr": 0.667, "+/-": 5.0, "name": "Eric Gordon", "USG%": 18.3, "DRB%": 7.5, "TS%": 0.9020618556701031, "experience": 4, "height": 1.9507437210436478, "2P%": 1.0, "MP": 17.733333333333334, "DRtg": 117.0, "ORtg": 104.0, "TRB%": 3.6, "FT/FGA": 0.6666666666666666, "ORB": 0.0, "3P%": 0.5, "HOB": 0.125}, "Xavier Henry": {"STL%": 3.2, "": "be", "FT": 3.0, "weight": "220", "3P": 0.0, "TOV": 1.0, "STL/TOV": 1.0, "TSA": 6.76, "2PA": 5.0, "college": "University of Kansas", "FG": 0.0, "3PA": 0.0, "DRB": 1.0, "ORB%": 7.0, "BLK%": 0.0, "AST/TOV": 0.0, "position": "SF", "AST": 0.0, "FT%": 0.75, "3PAr": 0.0, "PF": 0.0, "PTS": 3.0, "FGA": 5.0, "DRBr": 0.5, "ORBr": 0.5, "2P": 0.0, "STL": 1.0, "TRB": 2.0, "TOV%": 12.9, "AST%": 0.0, "FTAr": 0.8, "FTA": 4.0, "FIC": -0.5, "eFG%": 0.0, "BLK": 0.0, "birth_date": "1991-03-15", "FG%": 0.0, "2PAr": 1.0, "FTr": 0.8, "+/-": -22.0, "name": "Xavier Henry", "USG%": 20.9, "DRB%": 7.6, "TS%": 0.22189349112426035, "experience": 2, "height": 2.0117044623262617, "2P%": 0.0, "MP": 17.483333333333334, "DRtg": 110.0, "ORtg": 55.0, "TRB%": 7.3, "FT/FGA": 0.6, "ORB": 1.0, "3P%": null, "HOB": 0.0}, "Ryan Anderson": {"STL%": 0.0, "": "us", "FT": 4.0, "weight": "240", "3P": 0.0, "TOV": 3.0, "STL/TOV": 0.0, "TSA": 11.76, "2PA": 6.0, "college": "University of California", "FG": 0.0, "3PA": 4.0, "DRB": 3.0, "ORB%": 16.0, "BLK%": 4.1, "AST/TOV": 0.0, "position": "PF", "AST": 0.0, "FT%": 1.0, "3PAr": 0.4, "PF": 2.0, "PTS": 4.0, "FGA": 10.0, "DRBr": 0.5, "ORBr": 0.5, "2P": 0.0, "STL": 0.0, "TRB": 6.0, "TOV%": 20.3, "AST%": 0.0, "FTAr": 0.4, "FTA": 4.0, "FIC": -2.75, "eFG%": 0.0, "BLK": 1.0, "birth_date": "1988-05-06", "FG%": 0.0, "2PAr": 0.6, "FTr": 0.4, "+/-": -21.0, "name": "Ryan Anderson", "USG%": 30.1, "DRB%": 17.3, "TS%": 0.17006802721088435, "experience": 4, "height": 1.8593026091197267, "2P%": 0.0, "MP": 23.083333333333332, "DRtg": 112.0, "ORtg": 44.0, "TRB%": 16.6, "FT/FGA": 0.4, "ORB": 3.0, "3P%": 0.0, "HOB": 0.0}, "Al-Farouq Aminu": {"STL%": 6.7, "": "us", "FT": 0.0, "weight": "220", "3P": 0.0, "TOV": 2.0, "STL/TOV": 2.0, "TSA": 11.0, "2PA": 10.0, "college": "Wake Forest University", "FG": 4.0, "3PA": 1.0, "DRB": 2.0, "ORB%": 3.7, "BLK%": 0.0, "AST/TOV": 0.5, "position": "SF", "AST": 1.0, "FT%": null, "3PAr": 0.09090909090909091, "PF": 2.0, "PTS": 8.0, "FGA": 11.0, "DRBr": 0.6666666666666666, "ORBr": 0.3333333333333333, "2P": 4.0, "STL": 4.0, "TRB": 3.0, "TOV%": 15.4, "AST%": 5.5, "FTAr": 0.0, "FTA": 0.0, "FIC": 4.25, "eFG%": 0.36363636363636365, "BLK": 0.0, "birth_date": "1990-09-21", "FG%": 0.36363636363636365, "2PAr": 0.9090909090909091, "FTr": 0.0, "+/-": 3.0, "name": "Al-Farouq Aminu", "USG%": 18.4, "DRB%": 8.0, "TS%": 0.36363636363636365, "experience": 2, "height": 2.103145574250183, "2P%": 0.4, "MP": 33.25, "DRtg": 102.0, "ORtg": 75.0, "TRB%": 5.8, "FT/FGA": 0.0, "ORB": 1.0, "3P%": 0.0, "HOB": 0.15625}, "Lou Amundson": {"STL%": 0.0, "": "us", "FT": 0.0, "weight": "220", "3P": 0.0, "TOV": 0.0, "STL/TOV": null, "TSA": 1.0, "2PA": 1.0, "college": "University of Nevada, Las Vegas", "FG": 1.0, "3PA": 0.0, "DRB": 1.0, "ORB%": 19.4, "BLK%": 0.0, "AST/TOV": null, "position": "PF", "AST": 0.0, "FT%": null, "3PAr": 0.0, "PF": 2.0, "PTS": 2.0, "FGA": 1.0, "DRBr": 0.3333333333333333, "ORBr": 0.6666666666666666, "2P": 1.0, "STL": 0.0, "TRB": 3.0, "TOV%": 0.0, "AST%": 0.0, "FTAr": 0.0, "FTA": 0.0, "FIC": 3.0, "eFG%": 1.0, "BLK": 0.0, "birth_date": "1982-12-07", "FG%": 1.0, "2PAr": 1.0, "FTr": 0.0, "+/-": -15.0, "name": "Lou Amundson", "USG%": 3.7, "DRB%": 10.5, "TS%": 1.0, "experience": 6, "height": 2.103145574250183, "2P%": 1.0, "MP": 12.7, "DRtg": 116.0, "ORtg": 203.0, "TRB%": 15.1, "FT/FGA": 0.0, "ORB": 2.0, "3P%": null, "HOB": 0.03125}, "Brian Roberts": {"STL%": 0.0, "": "us", "FT": 0.0, "weight": "173", "3P": 0.0, "TOV": 2.0, "STL/TOV": 0.0, "TSA": 6.0, "2PA": 5.0, "college": "University of Dayton", "FG": 1.0, "3PA": 1.0, "DRB": 1.0, "ORB%": 0.0, "BLK%": 0.0, "AST/TOV": 0.0, "position": "PG", "AST": 0.0, "FT%": null, "3PAr": 0.16666666666666666, "PF": 4.0, "PTS": 2.0, "FGA": 6.0, "DRBr": 1.0, "ORBr": 0.0, "2P": 1.0, "STL": 0.0, "TRB": 1.0, "TOV%": 25.0, "AST%": 0.0, "FTAr": 0.0, "FTA": 0.0, "FIC": -5.75, "eFG%": 0.16666666666666666, "BLK": 0.0, "birth_date": "1985-12-03", "FG%": 0.16666666666666666, "2PAr": 0.8333333333333334, "FTr": 0.0, "+/-": -18.0, "name": "Brian Roberts", "USG%": 23.5, "DRB%": 8.3, "TS%": 0.16666666666666666, "experience": 0, "height": 1.8593026091197267, "2P%": 0.2, "MP": 16.05, "DRtg": 116.0, "ORtg": 29.0, "TRB%": 4.0, "FT/FGA": 0.0, "ORB": 0.0, "3P%": 0.0, "HOB": 0.03125}, "Anthony Davis": {"STL%": 0.0, "": "us", "FT": 4.0, "weight": "253", "3P": 0.0, "TOV": 0.0, "STL/TOV": null, "TSA": 18.2, "2PA": 16.0, "college": "University of Kentucky", "FG": 10.0, "3PA": 0.0, "DRB": 8.0, "ORB%": 15.9, "BLK%": 9.1, "AST/TOV": null, "position": "PF", "AST": 0.0, "FT%": 0.8, "3PAr": 0.0, "PF": 1.0, "PTS": 24.0, "FGA": 16.0, "DRBr": 0.6666666666666666, "ORBr": 0.3333333333333333, "2P": 10.0, "STL": 0.0, "TRB": 12.0, "TOV%": 0.0, "AST%": 0.0, "FTAr": 0.3125, "FTA": 5.0, "FIC": 22.625, "eFG%": 0.625, "BLK": 3.0, "birth_date": "1993-03-11", "FG%": 0.625, "2PAr": 1.0, "FTr": 0.313, "+/-": 10.0, "name": "Anthony Davis", "USG%": 27.8, "DRB%": 34.6, "TS%": 0.6593406593406593, "experience": 0, "height": 1.8593026091197267, "2P%": 0.625, "MP": 30.866666666666667, "DRtg": 104.0, "ORtg": 146.0, "TRB%": 24.9, "FT/FGA": 0.25, "ORB": 4.0, "3P%": null, "HOB": 0.3125}}, "scores": {"1": "24", "3": "24", "2": "19", "4": "16", "T": "83"}, "name": "New Orleans Hornets", "totals": {"STL%": 8.1, "FT": 17.0, "2PA": 65.0, "FG": 32.0, "DRB": 27.0, "ORB%": 33.3, "AST": 13.0, "3PAr": 0.15584415584415584, "PF": 20.0, "FGA": 77.0, "DRBr": 0.675, "2P": 30.0, "ORBr": 0.325, "TOV%": 15.7, "AST%": 40.6, "FTAr": 0.2597402597402597, "FIC": 50.0, "eFG%": 0.42857142857142855, "FG%": 0.4155844155844156, "2PAr": 0.8441558441558441, "+/-": -12.0, "USG%": 100.0, "DRtg": 110.3, "2P%": 0.46153846153846156, "DRB%": 75.0, "ORtg": 96.4, "TRB%": 53.3, "ORB": 13.0, "3P": 2.0, "TOV": 16.0, "STL/TOV": 0.4375, "TSA": 85.8, "AST/TOV": 0.8125, "3PA": 12.0, "BLK%": 9.8, "FT%": 0.85, "PTS": 83.0, "HOB": 1.40625, "STL": 7.0, "TRB": 40.0, "FTA": 20.0, "BLK": 5.0, "FTr": 0.26, "TS%": 0.4836829836829837, "FT/FGA": 0.22077922077922077, "3P%": 0.16666666666666666}}, "time": "19:00:00", "country": "United States", "date": "2013-04-05", "home": {"players": {"Gordon Hayward": {"STL%": 1.8, "": "us", "FT": 0.0, "weight": "226", "3P": 5.0, "TOV": 0.0, "STL/TOV": null, "TSA": 18.88, "2PA": 8.0, "college": "Butler University", "FG": 9.0, "3PA": 10.0, "DRB": 2.0, "ORB%": 0.0, "BLK%": 0.0, "AST/TOV": null, "position": "SF", "AST": 1.0, "FT%": 0.0, "3PAr": 0.5555555555555556, "PF": 2.0, "PTS": 23.0, "FGA": 18.0, "DRBr": 1.0, "ORBr": 0.0, "2P": 4.0, "STL": 1.0, "TRB": 2.0, "TOV%": 0.0, "AST%": 6.0, "FTAr": 0.1111111111111111, "FTA": 2.0, "FIC": 11.25, "eFG%": 0.6388888888888888, "BLK": 0.0, "birth_date": "1990-03-23", "FG%": 0.5, "2PAr": 0.4444444444444444, "FTr": 0.111, "+/-": -7.0, "name": "Gordon Hayward", "USG%": 29.5, "DRB%": 7.8, "TS%": 0.6091101694915254, "experience": 2, "height": 2.0726652036088757, "2P%": 0.5, "MP": 31.45, "DRtg": 102.0, "ORtg": 118.0, "TRB%": 4.1, "FT/FGA": 0.0, "ORB": 0.0, "3P%": 0.5, "HOB": 0.2564102564102564}, "Derrick Favors": {"STL%": 2.1, "": "us", "FT": 0.0, "weight": "265", "3P": 0.0, "TOV": 2.0, "STL/TOV": 0.5, "TSA": 8.0, "2PA": 8.0, "college": "Georgia Institute of Technology", "FG": 5.0, "3PA": 0.0, "DRB": 9.0, "ORB%": 5.0, "BLK%": 16.7, "AST/TOV": 0.0, "position": "PF", "AST": 0.0, "FT%": null, "3PAr": 0.0, "PF": 4.0, "PTS": 10.0, "FGA": 8.0, "DRBr": 0.9, "ORBr": 0.1, "2P": 5.0, "STL": 1.0, "TRB": 10.0, "TOV%": 20.0, "AST%": 0.0, "FTAr": 0.0, "FTA": 0.0, "FIC": 14.75, "eFG%": 0.625, "BLK": 6.0, "birth_date": "1991-07-15", "FG%": 0.625, "2PAr": 1.0, "FTr": 0.0, "+/-": 19.0, "name": "Derrick Favors", "USG%": 18.5, "DRB%": 41.7, "TS%": 0.625, "experience": 2, "height": 1.8593026091197267, "2P%": 0.625, "MP": 26.566666666666666, "DRtg": 78.0, "ORtg": 95.0, "TRB%": 24.1, "FT/FGA": 0.0, "ORB": 1.0, "3P%": null, "HOB": 0.1282051282051282}, "DeMarre Carroll": {"STL%": 6.5, "": "us", "FT": 1.0, "weight": "215", "3P": 1.0, "TOV": 1.0, "STL/TOV": 3.0, "TSA": 5.88, "2PA": 3.0, "college": "University of Missouri", "FG": 2.0, "3PA": 2.0, "DRB": 2.0, "ORB%": 5.2, "BLK%": 0.0, "AST/TOV": 3.0, "position": "SF", "AST": 3.0, "FT%": 0.5, "3PAr": 0.4, "PF": 3.0, "PTS": 6.0, "FGA": 5.0, "DRBr": 0.6666666666666666, "ORBr": 0.3333333333333333, "2P": 1.0, "STL": 3.0, "TRB": 3.0, "TOV%": 14.5, "AST%": 15.9, "FTAr": 0.4, "FTA": 2.0, "FIC": 7.5, "eFG%": 0.5, "BLK": 0.0, "birth_date": "1986-07-27", "FG%": 0.4, "2PAr": 0.6, "FTr": 0.4, "+/-": 21.0, "name": "DeMarre Carroll", "USG%": 13.1, "DRB%": 9.6, "TS%": 0.5102040816326531, "experience": 3, "height": 2.0726652036088757, "2P%": 0.3333333333333333, "MP": 25.7, "DRtg": 91.0, "ORtg": 111.0, "TRB%": 7.5, "FT/FGA": 0.2, "ORB": 1.0, "3P%": 0.5, "HOB": 0.1282051282051282}, "Randy Foye": {"STL%": 0.0, "": "us", "FT": 0.0, "weight": "213", "3P": 2.0, "TOV": 1.0, "STL/TOV": 0.0, "TSA": 9.0, "2PA": 2.0, "college": "Villanova University", "FG": 3.0, "3PA": 7.0, "DRB": 1.0, "ORB%": 0.0, "BLK%": 0.0, "AST/TOV": 4.0, "position": "SG", "AST": 4.0, "FT%": null, "3PAr": 0.7777777777777778, "PF": 1.0, "PTS": 8.0, "FGA": 9.0, "DRBr": 1.0, "ORBr": 0.0, "2P": 1.0, "STL": 0.0, "TRB": 1.0, "TOV%": 10.0, "AST%": 22.0, "FTAr": 0.0, "FTA": 0.0, "FIC": 4.5, "eFG%": 0.4444444444444444, "BLK": 0.0, "birth_date": "1983-09-24", "FG%": 0.3333333333333333, "2PAr": 0.2222222222222222, "FTr": 0.0, "+/-": -5.0, "name": "Randy Foye", "USG%": 18.8, "DRB%": 4.7, "TS%": 0.4444444444444444, "experience": 6, "height": 1.9507437210436478, "2P%": 0.5, "MP": 26.116666666666667, "DRtg": 107.0, "ORtg": 100.0, "TRB%": 2.5, "FT/FGA": 0.0, "ORB": 0.0, "3P%": 0.2857142857142857, "HOB": 0.1794871794871795}, "Mo Williams": {"STL%": 0.0, "": "us", "FT": 2.0, "weight": "198", "3P": 0.0, "TOV": 3.0, "STL/TOV": 0.0, "TSA": 8.88, "2PA": 6.0, "college": "University of Alabama", "FG": 3.0, "3PA": 2.0, "DRB": 2.0, "ORB%": 0.0, "BLK%": 0.0, "AST/TOV": 1.3333333333333333, "position": "PG", "AST": 4.0, "FT%": 1.0, "3PAr": 0.25, "PF": 4.0, "PTS": 8.0, "FGA": 8.0, "DRBr": 1.0, "ORBr": 0.0, "2P": 3.0, "STL": 0.0, "TRB": 2.0, "TOV%": 25.3, "AST%": 19.2, "FTAr": 0.25, "FTA": 2.0, "FIC": 1.75, "eFG%": 0.375, "BLK": 0.0, "birth_date": "1982-12-19", "FG%": 0.375, "2PAr": 0.75, "FTr": 0.25, "+/-": -5.0, "name": "Mo Williams", "USG%": 19.9, "DRB%": 8.4, "TS%": 0.4504504504504504, "experience": 9, "height": 1.8593026091197267, "2P%": 0.5, "MP": 29.333333333333332, "DRtg": 106.0, "ORtg": 85.0, "TRB%": 4.4, "FT/FGA": 0.25, "ORB": 0.0, "3P%": 0.0, "HOB": 0.1794871794871795}, "Alec Burks": {"STL%": 0.0, "": "us", "FT": 0.0, "weight": "214", "3P": 1.0, "TOV": 2.0, "STL/TOV": 0.0, "TSA": 2.0, "2PA": 1.0, "college": "University of Colorado", "FG": 1.0, "3PA": 1.0, "DRB": 1.0, "ORB%": 0.0, "BLK%": 0.0, "AST/TOV": 0.5, "position": "SG", "AST": 1.0, "FT%": null, "3PAr": 0.5, "PF": 2.0, "PTS": 3.0, "FGA": 2.0, "DRBr": 1.0, "ORBr": 0.0, "2P": 0.0, "STL": 0.0, "TRB": 1.0, "TOV%": 50.0, "AST%": 10.7, "FTAr": 0.0, "FTA": 0.0, "FIC": 0.25, "eFG%": 0.75, "BLK": 0.0, "birth_date": "1991-07-20", "FG%": 0.5, "2PAr": 0.5, "FTr": 0.0, "+/-": 15.0, "name": "Alec Burks", "USG%": 15.4, "DRB%": 9.7, "TS%": 0.75, "experience": 1, "height": 2.0117044623262617, "2P%": 0.0, "MP": 12.733333333333333, "DRtg": 105.0, "ORtg": 72.0, "TRB%": 5.0, "FT/FGA": 0.0, "ORB": 0.0, "3P%": 1.0, "HOB": 0.05128205128205128}, "Jamaal Tinsley": {"STL%": 3.0, "": "us", "FT": 0.0, "weight": "195", "3P": 1.0, "TOV": 3.0, "STL/TOV": 0.3333333333333333, "TSA": 3.0, "2PA": 0.0, "college": "Iowa State University", "FG": 1.0, "3PA": 3.0, "DRB": 1.0, "ORB%": 0.0, "BLK%": 4.0, "AST/TOV": 2.3333333333333335, "position": "PG", "AST": 7.0, "FT%": null, "3PAr": 1.0, "PF": 3.0, "PTS": 3.0, "FGA": 3.0, "DRBr": 1.0, "ORBr": 0.0, "2P": 0.0, "STL": 1.0, "TRB": 1.0, "TOV%": 50.0, "AST%": 49.4, "FTAr": 0.0, "FTA": 0.0, "FIC": 6.0, "eFG%": 0.5, "BLK": 1.0, "birth_date": "1978-02-28", "FG%": 0.3333333333333333, "2PAr": 0.0, "FTr": 0.0, "+/-": 17.0, "name": "Jamaal Tinsley", "USG%": 15.8, "DRB%": 6.6, "TS%": 0.5, "experience": 9, "height": 1.9202633504023408, "2P%": null, "MP": 18.666666666666668, "DRtg": 98.0, "ORtg": 95.0, "TRB%": 3.4, "FT/FGA": 0.0, "ORB": 0.0, "3P%": 0.3333333333333333, "HOB": 0.20512820512820512}, "Paul Millsap": {"STL%": 1.4, "": "us", "FT": 3.0, "weight": "246", "3P": 1.0, "TOV": 3.0, "STL/TOV": 0.3333333333333333, "TSA": 15.2, "2PA": 12.0, "college": "Louisiana Tech University", "FG": 8.0, "3PA": 1.0, "DRB": 4.0, "ORB%": 20.7, "BLK%": 1.9, "AST/TOV": 2.3333333333333335, "position": "PF", "AST": 7.0, "FT%": 0.6, "3PAr": 0.07692307692307693, "PF": 5.0, "PTS": 20.0, "FGA": 13.0, "DRBr": 0.4, "ORBr": 0.6, "2P": 7.0, "STL": 1.0, "TRB": 10.0, "TOV%": 16.5, "AST%": 29.8, "FTAr": 0.38461538461538464, "FTA": 5.0, "FIC": 20.875, "eFG%": 0.6538461538461539, "BLK": 1.0, "birth_date": "1985-02-10", "FG%": 0.6153846153846154, "2PAr": 0.9230769230769231, "FTr": 0.385, "+/-": 11.0, "name": "Paul Millsap", "USG%": 23.1, "DRB%": 12.7, "TS%": 0.6578947368421053, "experience": 6, "height": 2.0726652036088757, "2P%": 0.5833333333333334, "MP": 38.733333333333334, "DRtg": 100.0, "ORtg": 131.0, "TRB%": 16.5, "FT/FGA": 0.23076923076923078, "ORB": 6.0, "3P%": 1.0, "HOB": 0.38461538461538464}, "Al Jefferson": {"STL%": 5.4, "": "us", "FT": 0.0, "weight": "289", "3P": 0.0, "TOV": 1.0, "STL/TOV": 3.0, "TSA": 11.0, "2PA": 11.0, "college": "", "FG": 7.0, "3PA": 0.0, "DRB": 4.0, "ORB%": 4.3, "BLK%": 0.0, "AST/TOV": 1.0, "position": "C", "AST": 1.0, "FT%": null, "3PAr": 0.0, "PF": 1.0, "PTS": 14.0, "FGA": 11.0, "DRBr": 0.8, "ORBr": 0.2, "2P": 7.0, "STL": 3.0, "TRB": 5.0, "TOV%": 8.3, "AST%": 5.6, "FTAr": 0.0, "FTA": 0.0, "FIC": 12.25, "eFG%": 0.6363636363636364, "BLK": 0.0, "birth_date": "1985-01-04", "FG%": 0.6363636363636364, "2PAr": 1.0, "FTr": 0.0, "+/-": -6.0, "name": "Al Jefferson", "USG%": 19.2, "DRB%": 16.0, "TS%": 0.6363636363636364, "experience": 8, "height": 1.8593026091197267, "2P%": 0.6363636363636364, "MP": 30.7, "DRtg": 91.0, "ORtg": 117.0, "TRB%": 10.4, "FT/FGA": 0.0, "ORB": 1.0, "3P%": null, "HOB": 0.20512820512820512}}, "scores": {"1": "17", "3": "26", "2": "28", "4": "24", "T": "95"}, "name": "Utah Jazz", "totals": {"STL%": 11.6, "FT": 6.0, "2PA": 51.0, "FG": 39.0, "DRB": 26.0, "ORB%": 25.0, "AST": 28.0, "3PAr": 0.33766233766233766, "PF": 25.0, "FGA": 77.0, "DRBr": 0.7428571428571429, "2P": 28.0, "ORBr": 0.2571428571428571, "TOV%": 16.4, "AST%": 71.8, "FTAr": 0.14285714285714285, "FIC": 79.125, "eFG%": 0.577922077922078, "FG%": 0.5064935064935064, "2PAr": 0.6623376623376623, "+/-": 12.0, "USG%": 100.0, "DRtg": 96.4, "2P%": 0.5490196078431373, "DRB%": 66.7, "ORtg": 110.3, "TRB%": 46.7, "ORB": 9.0, "3P": 11.0, "TOV": 16.0, "STL/TOV": 0.625, "TSA": 81.84, "AST/TOV": 1.75, "3PA": 26.0, "BLK%": 12.3, "FT%": 0.5454545454545454, "PTS": 95.0, "HOB": 1.7179487179487178, "STL": 10.0, "TRB": 35.0, "FTA": 11.0, "BLK": 8.0, "FTr": 0.143, "TS%": 0.5804007820136852, "FT/FGA": 0.07792207792207792, "3P%": 0.4230769230769231}}, "type": "Season"}